[
  {
    "id": 1,
    "theme": "行動流域",
    "title": "打破拖延的循環",
    "content": "每個行動都是改變的種子。",
    "question": "此刻我可以採取哪個最小的行動？",
    "breath": "energize",
    "color": "#FFE8D6"
  },
  {
    "id": 2,
    "theme": "共感流域",
    "title": "同理心的力量",
    "content": "聆聽比建議更重要。",
    "question": "我想被誰理解？我準備好了嗎？",
    "breath": "gentle",
    "color": "#D8E3E8"
  },
  {
    "id": 3,
    "theme": "修復流域",
    "title": "允許自己慢下來",
    "content": "給自己時間復原。",
    "question": "什麼能讓我感到被照顧？",
    "breath": "restore",
    "color": "#E8F4E8"
  },
  {
    "id": 4,
    "theme": "接納流域",
    "title": "允許不完美存在",
    "content": "你已經夠好了。",
    "question": "什麼讓我覺得自己不夠好？",
    "breath": "gentle",
    "color": "#F0E8F4"
  },
  {
    "id": 5,
    "theme": "專注流域",
    "title": "專注於眼前",
    "content": "當下是唯一真實存在的時刻。",
    "question": "此刻我的感受是什麼？",
    "breath": "focus",
    "color": "#E8F0F8"
  },
  {
    "id": 6,
    "theme": "希望流域",
    "title": "困難終會過去",
    "content": "希望讓我們繼續前行。",
    "question": "我想創造什麼樣的未來？",
    "breath": "hope",
    "color": "#FFF4E8"
  },
  {
    "id": 7,
    "theme": "平靜流域",
    "title": "接受不確定",
    "content": "寧靜來自內在。",
    "question": "如何在不確定中找到安定？",
    "breath": "calm",
    "color": "#E8F4F8"
  },
  {
    "id": 8,
    "theme": "行動流域",
    "title": "小步前進也是進步",
    "content": "開始永遠不會太遲。",
    "question": "什麼阻止了我開始？",
    "breath": "energize",
    "color": "#FFE8D6"
  },
  {
    "id": 9,
    "theme": "共感流域",
    "title": "真誠的對話",
    "content": "同在就是支持。",
    "question": "此刻我需要什麼樣的陪伴？",
    "breath": "gentle",
    "color": "#D8E3E8"
  },
  {
    "id": 10,
    "theme": "修復流域",
    "title": "允許自己慢下來",
    "content": "修復是持續的過程。",
    "question": "此刻我的身體想告訴我什麼？",
    "breath": "restore",
    "color": "#E8F4E8"
  },
  {
    "id": 11,
    "theme": "接納流域",
    "title": "允許不完美存在",
    "content": "接納帶來自由。",
    "question": "我能接納自己的哪個部分？",
    "breath": "gentle",
    "color": "#F0E8F4"
  },
  {
    "id": 12,
    "theme": "專注流域",
    "title": "活在當下",
    "content": "覺察就是力量。",
    "question": "此刻我的感受是什麼？",
    "breath": "focus",
    "color": "#E8F0F8"
  },
  {
    "id": 13,
    "theme": "希望流域",
    "title": "保持期待",
    "content": "未來充滿驚喜。",
    "question": "什麼讓我感到有希望？",
    "breath": "hope",
    "color": "#FFF4E8"
  },
  {
    "id": 14,
    "theme": "平靜流域",
    "title": "內在的平靜",
    "content": "放下才能平靜。",
    "question": "此刻什麼能讓我感到平靜？",
    "breath": "calm",
    "color": "#E8F4F8"
  },
  {
    "id": 15,
    "theme": "行動流域",
    "title": "行動創造可能",
    "content": "一步步靠近理想。",
    "question": "此刻我可以採取哪個最小的行動？",
    "breath": "energize",
    "color": "#FFE8D6"
  },
  {
    "id": 16,
    "theme": "共感流域",
    "title": "在關係中成長",
    "content": "表達需要也需要勇氣。",
    "question": "我想被誰理解？我準備好了嗎？",
    "breath": "gentle",
    "color": "#D8E3E8"
  },
  {
    "id": 17,
    "theme": "修復流域",
    "title": "允許自己慢下來",
    "content": "療癒不需要完美，只需要開始。",
    "question": "此刻我的身體想告訴我什麼？",
    "breath": "restore",
    "color": "#E8F4E8"
  },
  {
    "id": 18,
    "theme": "接納流域",
    "title": "放下自我批判",
    "content": "完整包含光明與陰影。",
    "question": "我能接納自己的哪個部分？",
    "breath": "gentle",
    "color": "#F0E8F4"
  },
  {
    "id": 19,
    "theme": "專注流域",
    "title": "當下是唯一真實",
    "content": "當下是唯一真實存在的時刻。",
    "question": "我在擔心什麼還未發生的事？",
    "breath": "focus",
    "color": "#E8F0F8"
  },
  {
    "id": 20,
    "theme": "希望流域",
    "title": "黎明前的黑暗",
    "content": "每個今天都是新的開始。",
    "question": "我想創造什麼樣的未來？",
    "breath": "hope",
    "color": "#FFF4E8"
  },
  {
    "id": 21,
    "theme": "平靜流域",
    "title": "接受不確定",
    "content": "在當下找到安定。",
    "question": "如何在不確定中找到安定？",
    "breath": "calm",
    "color": "#E8F4F8"
  },
  {
    "id": 22,
    "theme": "行動流域",
    "title": "打破拖延的循環",
    "content": "每個行動都是改變的種子。",
    "question": "完成這件事會帶給我什麼？",
    "breath": "energize",
    "color": "#FFE8D6"
  },
  {
    "id": 23,
    "theme": "共感流域",
    "title": "同理心的力量",
    "content": "表達需要也需要勇氣。",
    "question": "我想被誰理解？我準備好了嗎？",
    "breath": "gentle",
    "color": "#D8E3E8"
  },
  {
    "id": 24,
    "theme": "修復流域",
    "title": "允許自己慢下來",
    "content": "休息是為了走更長的路。",
    "question": "什麼能讓我感到被照顧？",
    "breath": "restore",
    "color": "#E8F4E8"
  },
  {
    "id": 25,
    "theme": "接納流域",
    "title": "擁抱真實的自己",
    "content": "你已經夠好了。",
    "question": "我能接納自己的哪個部分？",
    "breath": "gentle",
    "color": "#F0E8F4"
  },
  {
    "id": 26,
    "theme": "專注流域",
    "title": "當下是唯一真實",
    "content": "當下是唯一真實存在的時刻。",
    "question": "如何將注意力帶回此刻？",
    "breath": "focus",
    "color": "#E8F0F8"
  },
  {
    "id": 27,
    "theme": "希望流域",
    "title": "每天都是新開始",
    "content": "相信總會好轉。",
    "question": "我對未來抱持什麼樣的期待？",
    "breath": "hope",
    "color": "#FFF4E8"
  },
  {
    "id": 28,
    "theme": "平靜流域",
    "title": "在混亂中保持平靜",
    "content": "平靜是一種選擇。",
    "question": "如何在不確定中找到安定？",
    "breath": "calm",
    "color": "#E8F4F8"
  },
  {
    "id": 29,
    "theme": "行動流域",
    "title": "相信行動的力量",
    "content": "行動帶來清晰。",
    "question": "完成這件事會帶給我什麼？",
    "breath": "energize",
    "color": "#FFE8D6"
  },
  {
    "id": 30,
    "theme": "共感流域",
    "title": "同理心的力量",
    "content": "脆弱是連結的開始。",
    "question": "我想被誰理解？我準備好了嗎？",
    "breath": "gentle",
    "color": "#D8E3E8"
  },
  {
    "id": 31,
    "theme": "修復流域",
    "title": "溫柔對待自己",
    "content": "休息是為了走更長的路。",
    "question": "什麼能讓我感到被照顧？",
    "breath": "restore",
    "color": "#E8F4E8"
  },
  {
    "id": 32,
    "theme": "接納流域",
    "title": "不完美也值得被愛",
    "content": "接納帶來自由。",
    "question": "什麼讓我覺得自己不夠好？",
    "breath": "gentle",
    "color": "#F0E8F4"
  },
  {
    "id": 33,
    "theme": "專注流域",
    "title": "放下過去與未來",
    "content": "專注創造品質。",
    "question": "我在擔心什麼還未發生的事？",
    "breath": "focus",
    "color": "#E8F0F8"
  },
  {
    "id": 34,
    "theme": "希望流域",
    "title": "相信改變的力量",
    "content": "希望讓我們繼續前行。",
    "question": "我對未來抱持什麼樣的期待？",
    "breath": "hope",
    "color": "#FFF4E8"
  },
  {
    "id": 35,
    "theme": "平靜流域",
    "title": "內在的平靜",
    "content": "接受帶來安定。",
    "question": "如何在不確定中找到安定？",
    "breath": "calm",
    "color": "#E8F4F8"
  },
  {
    "id": 36,
    "theme": "行動流域",
    "title": "小步前進也是進步",
    "content": "開始永遠不會太遲。",
    "question": "此刻我可以採取哪個最小的行動？",
    "breath": "energize",
    "color": "#FFE8D6"
  },
  {
    "id": 37,
    "theme": "共感流域",
    "title": "被看見被接住",
    "content": "脆弱是連結的開始。",
    "question": "此刻我需要什麼樣的陪伴？",
    "breath": "gentle",
    "color": "#D8E3E8"
  },
  {
    "id": 38,
    "theme": "修復流域",
    "title": "療癒需要耐心",
    "content": "療癒不需要完美，只需要開始。",
    "question": "此刻我需要如何被理解，才能感覺安心？",
    "breath": "restore",
    "color": "#E8F4E8"
  },
  {
    "id": 39,
    "theme": "接納流域",
    "title": "接納全部的自己",
    "content": "你已經夠好了。",
    "question": "我能接納自己的哪個部分？",
    "breath": "gentle",
    "color": "#F0E8F4"
  },
  {
    "id": 40,
    "theme": "專注流域",
    "title": "一次只做一件事",
    "content": "專注創造品質。",
    "question": "此刻我的感受是什麼？",
    "breath": "focus",
    "color": "#E8F0F8"
  },
  {
    "id": 41,
    "theme": "希望流域",
    "title": "保持期待",
    "content": "可能性永遠存在。",
    "question": "我對未來抱持什麼樣的期待？",
    "breath": "hope",
    "color": "#FFF4E8"
  },
  {
    "id": 42,
    "theme": "平靜流域",
    "title": "讓心安住在寧靜中",
    "content": "寧靜來自內在。",
    "question": "我在抗拒什麼？",
    "breath": "calm",
    "color": "#E8F4F8"
  },
  {
    "id": 43,
    "theme": "行動流域",
    "title": "行動創造可能",
    "content": "行動帶來清晰。",
    "question": "此刻我可以採取哪個最小的行動？",
    "breath": "energize",
    "color": "#FFE8D6"
  },
  {
    "id": 44,
    "theme": "共感流域",
    "title": "脆弱是勇氣",
    "content": "脆弱是連結的開始。",
    "question": "我想被誰理解？我準備好了嗎？",
    "breath": "gentle",
    "color": "#D8E3E8"
  },
  {
    "id": 45,
    "theme": "修復流域",
    "title": "給自己一點修復的時間",
    "content": "情緒需要被感受而非壓抑。",
    "question": "此刻我的身體想告訴我什麼？",
    "breath": "restore",
    "color": "#E8F4E8"
  },
  {
    "id": 46,
    "theme": "接納流域",
    "title": "允許不完美存在",
    "content": "完整包含光明與陰影。",
    "question": "什麼讓我覺得自己不夠好？",
    "breath": "gentle",
    "color": "#F0E8F4"
  },
  {
    "id": 47,
    "theme": "專注流域",
    "title": "一次只做一件事",
    "content": "當下是唯一真實存在的時刻。",
    "question": "如何將注意力帶回此刻？",
    "breath": "focus",
    "color": "#E8F0F8"
  },
  {
    "id": 48,
    "theme": "希望流域",
    "title": "希望是光",
    "content": "相信總會好轉。",
    "question": "我想創造什麼樣的未來？",
    "breath": "hope",
    "color": "#FFF4E8"
  },
  {
    "id": 49,
    "theme": "平靜流域",
    "title": "讓心安住在寧靜中",
    "content": "平靜是一種選擇。",
    "question": "此刻什麼能讓我感到平靜？",
    "breath": "calm",
    "color": "#E8F4F8"
  },
  {
    "id": 50,
    "theme": "行動流域",
    "title": "小步前進也是進步",
    "content": "行動帶來清晰。",
    "question": "什麼阻止了我開始？",
    "breath": "energize",
    "color": "#FFE8D6"
  },
  {
    "id": 51,
    "theme": "共感流域",
    "title": "真誠的對話",
    "content": "脆弱是連結的開始。",
    "question": "我能如何更真誠地表達？",
    "breath": "gentle",
    "color": "#D8E3E8"
  },
  {
    "id": 52,
    "theme": "修復流域",
    "title": "給自己一點修復的時間",
    "content": "修復是持續的過程。",
    "question": "此刻我需要如何被理解，才能感覺安心？",
    "breath": "restore",
    "color": "#E8F4E8"
  },
  {
    "id": 53,
    "theme": "接納流域",
    "title": "允許不完美存在",
    "content": "完整包含光明與陰影。",
    "question": "如果接納自己，會發生什麼？",
    "breath": "gentle",
    "color": "#F0E8F4"
  },
  {
    "id": 54,
    "theme": "專注流域",
    "title": "一次只做一件事",
    "content": "當下是唯一真實存在的時刻。",
    "question": "我在擔心什麼還未發生的事？",
    "breath": "focus",
    "color": "#E8F0F8"
  },
  {
    "id": 55,
    "theme": "希望流域",
    "title": "黎明前的黑暗",
    "content": "可能性永遠存在。",
    "question": "我對未來抱持什麼樣的期待？",
    "breath": "hope",
    "color": "#FFF4E8"
  },
  {
    "id": 56,
    "theme": "平靜流域",
    "title": "寧靜是答案",
    "content": "在當下找到安定。",
    "question": "如何在不確定中找到安定？",
    "breath": "calm",
    "color": "#E8F4F8"
  },
  {
    "id": 57,
    "theme": "行動流域",
    "title": "勇敢嘗試新事物",
    "content": "前進比完美更重要。",
    "question": "完成這件事會帶給我什麼？",
    "breath": "energize",
    "color": "#FFE8D6"
  },
  {
    "id": 58,
    "theme": "共感流域",
    "title": "被看見被接住",
    "content": "理解不需要相同。",
    "question": "我想被誰理解？我準備好了嗎？",
    "breath": "gentle",
    "color": "#D8E3E8"
  },
  {
    "id": 59,
    "theme": "修復流域",
    "title": "修復是一種智慧",
    "content": "給自己時間復原。",
    "question": "什麼能讓我感到被照顧？",
    "breath": "restore",
    "color": "#E8F4E8"
  },
  {
    "id": 60,
    "theme": "接納流域",
    "title": "這樣的我也很好",
    "content": "接納是成長的開始。",
    "question": "什麼讓我覺得自己不夠好？",
    "breath": "gentle",
    "color": "#F0E8F4"
  },
  {
    "id": 61,
    "theme": "專注流域",
    "title": "當下是唯一真實",
    "content": "活在當下減少焦慮。",
    "question": "我在擔心什麼還未發生的事？",
    "breath": "focus",
    "color": "#E8F0F8"
  },
  {
    "id": 62,
    "theme": "希望流域",
    "title": "每天都是新開始",
    "content": "希望讓我們繼續前行。",
    "question": "我想創造什麼樣的未來？",
    "breath": "hope",
    "color": "#FFF4E8"
  },
  {
    "id": 63,
    "theme": "平靜流域",
    "title": "讓心安住在寧靜中",
    "content": "平靜不是沒有風浪，而是學會與之共處。",
    "question": "此刻什麼能讓我感到平靜？",
    "breath": "calm",
    "color": "#E8F4F8"
  },
  {
    "id": 64,
    "theme": "行動流域",
    "title": "現在就是最好的時機",
    "content": "開始永遠不會太遲。",
    "question": "什麼阻止了我開始？",
    "breath": "energize",
    "color": "#FFE8D6"
  },
  {
    "id": 65,
    "theme": "共感流域",
    "title": "允許自己被理解",
    "content": "真實的自己值得被愛。",
    "question": "我能如何更真誠地表達？",
    "breath": "gentle",
    "color": "#D8E3E8"
  },
  {
    "id": 66,
    "theme": "修復流域",
    "title": "允許自己慢下來",
    "content": "情緒需要被感受而非壓抑。",
    "question": "此刻我的身體想告訴我什麼？",
    "breath": "restore",
    "color": "#E8F4E8"
  },
  {
    "id": 67,
    "theme": "接納流域",
    "title": "放下自我批判",
    "content": "你已經夠好了。",
    "question": "什麼讓我覺得自己不夠好？",
    "breath": "gentle",
    "color": "#F0E8F4"
  },
  {
    "id": 68,
    "theme": "專注流域",
    "title": "放下過去與未來",
    "content": "活在當下減少焦慮。",
    "question": "此刻我的感受是什麼？",
    "breath": "focus",
    "color": "#E8F0F8"
  },
  {
    "id": 69,
    "theme": "希望流域",
    "title": "希望是光",
    "content": "未來充滿驚喜。",
    "question": "我對未來抱持什麼樣的期待？",
    "breath": "hope",
    "color": "#FFF4E8"
  },
  {
    "id": 70,
    "theme": "平靜流域",
    "title": "寧靜是答案",
    "content": "接受帶來安定。",
    "question": "此刻什麼能讓我感到平靜？",
    "breath": "calm",
    "color": "#E8F4F8"
  },
  {
    "id": 71,
    "theme": "行動流域",
    "title": "行動創造可能",
    "content": "行動帶來清晰。",
    "question": "此刻我可以採取哪個最小的行動？",
    "breath": "energize",
    "color": "#FFE8D6"
  },
  {
    "id": 72,
    "theme": "共感流域",
    "title": "在關係中成長",
    "content": "脆弱是連結的開始。",
    "question": "我想被誰理解？我準備好了嗎？",
    "breath": "gentle",
    "color": "#D8E3E8"
  },
  {
    "id": 73,
    "theme": "修復流域",
    "title": "療癒需要耐心",
    "content": "休息是為了走更長的路。",
    "question": "此刻我的身體想告訴我什麼？",
    "breath": "restore",
    "color": "#E8F4E8"
  },
  {
    "id": 74,
    "theme": "接納流域",
    "title": "善待內在小孩",
    "content": "不完美的自己，也值得被愛。",
    "question": "什麼讓我覺得自己不夠好？",
    "breath": "gentle",
    "color": "#F0E8F4"
  },
  {
    "id": 75,
    "theme": "專注流域",
    "title": "一次只做一件事",
    "content": "當下是唯一真實存在的時刻。",
    "question": "如何將注意力帶回此刻？",
    "breath": "focus",
    "color": "#E8F0F8"
  },
  {
    "id": 76,
    "theme": "希望流域",
    "title": "未來仍有無限可能",
    "content": "困境是暫時的。",
    "question": "我對未來抱持什麼樣的期待？",
    "breath": "hope",
    "color": "#FFF4E8"
  },
  {
    "id": 77,
    "theme": "平靜流域",
    "title": "平靜來自接納",
    "content": "平靜是一種選擇。",
    "question": "我在抗拒什麼？",
    "breath": "calm",
    "color": "#E8F4F8"
  },
  {
    "id": 78,
    "theme": "行動流域",
    "title": "現在就是最好的時機",
    "content": "從小事開始改變。",
    "question": "什麼阻止了我開始？",
    "breath": "energize",
    "color": "#FFE8D6"
  },
  {
    "id": 79,
    "theme": "共感流域",
    "title": "同理心的力量",
    "content": "表達需要也需要勇氣。",
    "question": "我能如何更真誠地表達？",
    "breath": "gentle",
    "color": "#D8E3E8"
  },
  {
    "id": 80,
    "theme": "修復流域",
    "title": "療癒需要耐心",
    "content": "情緒需要被感受而非壓抑。",
    "question": "什麼能讓我感到被照顧？",
    "breath": "restore",
    "color": "#E8F4E8"
  },
  {
    "id": 81,
    "theme": "接納流域",
    "title": "擁抱真實的自己",
    "content": "完整包含光明與陰影。",
    "question": "如果接納自己，會發生什麼？",
    "breath": "gentle",
    "color": "#F0E8F4"
  },
  {
    "id": 82,
    "theme": "專注流域",
    "title": "回到此刻的呼吸",
    "content": "活在當下減少焦慮。",
    "question": "如何將注意力帶回此刻？",
    "breath": "focus",
    "color": "#E8F0F8"
  },
  {
    "id": 83,
    "theme": "希望流域",
    "title": "相信改變的力量",
    "content": "相信總會好轉。",
    "question": "我想創造什麼樣的未來？",
    "breath": "hope",
    "color": "#FFF4E8"
  },
  {
    "id": 84,
    "theme": "平靜流域",
    "title": "在混亂中保持平靜",
    "content": "平靜是一種選擇。",
    "question": "如何在不確定中找到安定？",
    "breath": "calm",
    "color": "#E8F4F8"
  },
  {
    "id": 85,
    "theme": "行動流域",
    "title": "踏出第一步",
    "content": "從小事開始改變。",
    "question": "此刻我可以採取哪個最小的行動？",
    "breath": "energize",
    "color": "#FFE8D6"
  },
  {
    "id": 86,
    "theme": "共感流域",
    "title": "在關係中成長",
    "content": "表達需要也需要勇氣。",
    "question": "我想被誰理解？我準備好了嗎？",
    "breath": "gentle",
    "color": "#D8E3E8"
  },
  {
    "id": 87,
    "theme": "修復流域",
    "title": "身心需要休息",
    "content": "情緒需要被感受而非壓抑。",
    "question": "此刻我的身體想告訴我什麼？",
    "breath": "restore",
    "color": "#E8F4E8"
  },
  {
    "id": 88,
    "theme": "接納流域",
    "title": "放下自我批判",
    "content": "不完美的自己，也值得被愛。",
    "question": "如果接納自己，會發生什麼？",
    "breath": "gentle",
    "color": "#F0E8F4"
  },
  {
    "id": 89,
    "theme": "專注流域",
    "title": "當下是唯一真實",
    "content": "當下是唯一真實存在的時刻。",
    "question": "如何將注意力帶回此刻？",
    "breath": "focus",
    "color": "#E8F0F8"
  },
  {
    "id": 90,
    "theme": "希望流域",
    "title": "每天都是新開始",
    "content": "希望讓我們繼續前行。",
    "question": "我想創造什麼樣的未來？",
    "breath": "hope",
    "color": "#FFF4E8"
  },
  {
    "id": 91,
    "theme": "平靜流域",
    "title": "平靜來自接納",
    "content": "放下才能平靜。",
    "question": "此刻什麼能讓我感到平靜？",
    "breath": "calm",
    "color": "#E8F4F8"
  },
  {
    "id": 92,
    "theme": "行動流域",
    "title": "行動創造可能",
    "content": "一步步靠近理想。",
    "question": "此刻我可以採取哪個最小的行動？",
    "breath": "energize",
    "color": "#FFE8D6"
  },
  {
    "id": 93,
    "theme": "共感流域",
    "title": "理解彼此的差異",
    "content": "同在就是支持。",
    "question": "此刻我需要什麼樣的陪伴？",
    "breath": "gentle",
    "color": "#D8E3E8"
  },
  {
    "id": 94,
    "theme": "修復流域",
    "title": "療癒需要耐心",
    "content": "療癒不需要完美，只需要開始。",
    "question": "此刻我需要如何被理解，才能感覺安心？",
    "breath": "restore",
    "color": "#E8F4E8"
  },
  {
    "id": 95,
    "theme": "接納流域",
    "title": "接納全部的自己",
    "content": "接納帶來自由。",
    "question": "什麼讓我覺得自己不夠好？",
    "breath": "gentle",
    "color": "#F0E8F4"
  },
  {
    "id": 96,
    "theme": "專注流域",
    "title": "放下過去與未來",
    "content": "活在當下減少焦慮。",
    "question": "我在擔心什麼還未發生的事？",
    "breath": "focus",
    "color": "#E8F0F8"
  },
  {
    "id": 97,
    "theme": "希望流域",
    "title": "未來仍有無限可能",
    "content": "希望讓我們繼續前行。",
    "question": "我想創造什麼樣的未來？",
    "breath": "hope",
    "color": "#FFF4E8"
  },
  {
    "id": 98,
    "theme": "平靜流域",
    "title": "在混亂中保持平靜",
    "content": "在當下找到安定。",
    "question": "此刻什麼能讓我感到平靜？",
    "breath": "calm",
    "color": "#E8F4F8"
  },
  {
    "id": 99,
    "theme": "行動流域",
    "title": "小步前進也是進步",
    "content": "前進比完美更重要。",
    "question": "完成這件事會帶給我什麼？",
    "breath": "energize",
    "color": "#FFE8D6"
  },
  {
    "id": 100,
    "theme": "共感流域",
    "title": "同理心的力量",
    "content": "理解不需要相同。",
    "question": "此刻我需要什麼樣的陪伴？",
    "breath": "gentle",
    "color": "#D8E3E8"
  },
  {
    "id": 101,
    "theme": "修復流域",
    "title": "修復是一種智慧",
    "content": "再向外分享溫柔與在意。",
    "question": "什麼能讓我感到被照顧？",
    "breath": "restore",
    "color": "#E8F4E8"
  },
  {
    "id": 102,
    "theme": "接納流域",
    "title": "擁抱真實的自己",
    "content": "你已經夠好了。",
    "question": "什麼讓我覺得自己不夠好？",
    "breath": "gentle",
    "color": "#F0E8F4"
  },
  {
    "id": 103,
    "theme": "專注流域",
    "title": "覺察此時此刻",
    "content": "覺察就是力量。",
    "question": "此刻我的感受是什麼？",
    "breath": "focus",
    "color": "#E8F0F8"
  },
  {
    "id": 104,
    "theme": "希望流域",
    "title": "困難終會過去",
    "content": "希望讓我們繼續前行。",
    "question": "什麼讓我感到有希望？",
    "breath": "hope",
    "color": "#FFF4E8"
  },
  {
    "id": 105,
    "theme": "平靜流域",
    "title": "寧靜是答案",
    "content": "放下才能平靜。",
    "question": "如何在不確定中找到安定？",
    "breath": "calm",
    "color": "#E8F4F8"
  },
  {
    "id": 106,
    "theme": "行動流域",
    "title": "打破拖延的循環",
    "content": "從小事開始改變。",
    "question": "什麼阻止了我開始？",
    "breath": "energize",
    "color": "#FFE8D6"
  },
  {
    "id": 107,
    "theme": "共感流域",
    "title": "允許自己被理解",
    "content": "脆弱是連結的開始。",
    "question": "我想被誰理解？我準備好了嗎？",
    "breath": "gentle",
    "color": "#D8E3E8"
  },
  {
    "id": 108,
    "theme": "修復流域",
    "title": "接受情緒的起伏",
    "content": "修復是持續的過程。",
    "question": "什麼能讓我感到被照顧？",
    "breath": "restore",
    "color": "#E8F4E8"
  },
  {
    "id": 109,
    "theme": "接納流域",
    "title": "允許不完美存在",
    "content": "完整包含光明與陰影。",
    "question": "如果接納自己，會發生什麼？",
    "breath": "gentle",
    "color": "#F0E8F4"
  },
  {
    "id": 110,
    "theme": "專注流域",
    "title": "一次只做一件事",
    "content": "此刻就是全部。",
    "question": "如何將注意力帶回此刻？",
    "breath": "focus",
    "color": "#E8F0F8"
  },
  {
    "id": 111,
    "theme": "希望流域",
    "title": "相信美好會到來",
    "content": "相信總會好轉。",
    "question": "我對未來抱持什麼樣的期待？",
    "breath": "hope",
    "color": "#FFF4E8"
  },
  {
    "id": 112,
    "theme": "平靜流域",
    "title": "在混亂中保持平靜",
    "content": "放下才能平靜。",
    "question": "此刻什麼能讓我感到平靜？",
    "breath": "calm",
    "color": "#E8F4F8"
  },
  {
    "id": 113,
    "theme": "行動流域",
    "title": "現在就是最好的時機",
    "content": "前進比完美更重要。",
    "question": "什麼阻止了我開始？",
    "breath": "energize",
    "color": "#FFE8D6"
  },
  {
    "id": 114,
    "theme": "共感流域",
    "title": "在關係中成長",
    "content": "理解不需要相同。",
    "question": "我能如何更真誠地表達？",
    "breath": "gentle",
    "color": "#D8E3E8"
  },
  {
    "id": 115,
    "theme": "修復流域",
    "title": "療癒需要耐心",
    "content": "療癒不需要完美，只需要開始。",
    "question": "此刻我的身體想告訴我什麼？",
    "breath": "restore",
    "color": "#E8F4E8"
  },
  {
    "id": 116,
    "theme": "接納流域",
    "title": "允許不完美存在",
    "content": "每個部分都有存在的意義。",
    "question": "什麼讓我覺得自己不夠好？",
    "breath": "gentle",
    "color": "#F0E8F4"
  },
  {
    "id": 117,
    "theme": "專注流域",
    "title": "回到此刻的呼吸",
    "content": "此刻就是全部。",
    "question": "如何將注意力帶回此刻？",
    "breath": "focus",
    "color": "#E8F0F8"
  },
  {
    "id": 118,
    "theme": "希望流域",
    "title": "希望是光",
    "content": "希望讓我們繼續前行。",
    "question": "什麼讓我感到有希望？",
    "breath": "hope",
    "color": "#FFF4E8"
  },
  {
    "id": 119,
    "theme": "平靜流域",
    "title": "平靜來自接納",
    "content": "平靜是一種選擇。",
    "question": "我在抗拒什麼？",
    "breath": "calm",
    "color": "#E8F4F8"
  },
  {
    "id": 120,
    "theme": "行動流域",
    "title": "現在就是最好的時機",
    "content": "從小事開始改變。",
    "question": "什麼阻止了我開始？",
    "breath": "energize",
    "color": "#FFE8D6"
  },
  {
    "id": 121,
    "theme": "共感流域",
    "title": "真誠的對話",
    "content": "聆聽比建議更重要。",
    "question": "我想被誰理解？我準備好了嗎？",
    "breath": "gentle",
    "color": "#D8E3E8"
  },
  {
    "id": 122,
    "theme": "修復流域",
    "title": "修復是一種智慧",
    "content": "情緒需要被感受而非壓抑。",
    "question": "此刻我的身體想告訴我什麼？",
    "breath": "restore",
    "color": "#E8F4E8"
  },
  {
    "id": 123,
    "theme": "接納流域",
    "title": "自我接納是力量",
    "content": "不完美的自己，也值得被愛。",
    "question": "如果接納自己，會發生什麼？",
    "breath": "gentle",
    "color": "#F0E8F4"
  },
  {
    "id": 124,
    "theme": "專注流域",
    "title": "回到此刻的呼吸",
    "content": "當下是唯一真實存在的時刻。",
    "question": "此刻我的感受是什麼？",
    "breath": "focus",
    "color": "#E8F0F8"
  },
  {
    "id": 125,
    "theme": "希望流域",
    "title": "每天都是新開始",
    "content": "可能性永遠存在。",
    "question": "我對未來抱持什麼樣的期待？",
    "breath": "hope",
    "color": "#FFF4E8"
  },
  {
    "id": 126,
    "theme": "平靜流域",
    "title": "平靜來自接納",
    "content": "接受帶來安定。",
    "question": "如何在不確定中找到安定？",
    "breath": "calm",
    "color": "#E8F4F8"
  },
  {
    "id": 127,
    "theme": "行動流域",
    "title": "打破拖延的循環",
    "content": "前進比完美更重要。",
    "question": "什麼阻止了我開始？",
    "breath": "energize",
    "color": "#FFE8D6"
  },
  {
    "id": 128,
    "theme": "共感流域",
    "title": "同理心的力量",
    "content": "真實的自己值得被愛。",
    "question": "我能如何更真誠地表達？",
    "breath": "gentle",
    "color": "#D8E3E8"
  },
  {
    "id": 129,
    "theme": "修復流域",
    "title": "給自己一點修復的時間",
    "content": "再向外分享溫柔與在意。",
    "question": "此刻我需要如何被理解，才能感覺安心？",
    "breath": "restore",
    "color": "#E8F4E8"
  },
  {
    "id": 130,
    "theme": "接納流域",
    "title": "接納全部的自己",
    "content": "接納帶來自由。",
    "question": "什麼讓我覺得自己不夠好？",
    "breath": "gentle",
    "color": "#F0E8F4"
  },
  {
    "id": 131,
    "theme": "專注流域",
    "title": "一次只做一件事",
    "content": "活在當下減少焦慮。",
    "question": "此刻我的感受是什麼？",
    "breath": "focus",
    "color": "#E8F0F8"
  },
  {
    "id": 132,
    "theme": "希望流域",
    "title": "困難終會過去",
    "content": "可能性永遠存在。",
    "question": "什麼讓我感到有希望？",
    "breath": "hope",
    "color": "#FFF4E8"
  },
  {
    "id": 133,
    "theme": "平靜流域",
    "title": "放下控制",
    "content": "在當下找到安定。",
    "question": "如何在不確定中找到安定？",
    "breath": "calm",
    "color": "#E8F4F8"
  },
  {
    "id": 134,
    "theme": "行動流域",
    "title": "勇敢嘗試新事物",
    "content": "從小事開始改變。",
    "question": "此刻我可以採取哪個最小的行動？",
    "breath": "energize",
    "color": "#FFE8D6"
  },
  {
    "id": 135,
    "theme": "共感流域",
    "title": "被看見被接住",
    "content": "聆聽比建議更重要。",
    "question": "此刻我需要什麼樣的陪伴？",
    "breath": "gentle",
    "color": "#D8E3E8"
  },
  {
    "id": 136,
    "theme": "修復流域",
    "title": "療癒需要耐心",
    "content": "給自己時間復原。",
    "question": "此刻我需要如何被理解，才能感覺安心？",
    "breath": "restore",
    "color": "#E8F4E8"
  },
  {
    "id": 137,
    "theme": "接納流域",
    "title": "接納全部的自己",
    "content": "完整包含光明與陰影。",
    "question": "如果接納自己，會發生什麼？",
    "breath": "gentle",
    "color": "#F0E8F4"
  },
  {
    "id": 138,
    "theme": "專注流域",
    "title": "覺察此時此刻",
    "content": "活在當下減少焦慮。",
    "question": "如何將注意力帶回此刻？",
    "breath": "focus",
    "color": "#E8F0F8"
  },
  {
    "id": 139,
    "theme": "希望流域",
    "title": "相信改變的力量",
    "content": "困境是暫時的。",
    "question": "我對未來抱持什麼樣的期待？",
    "breath": "hope",
    "color": "#FFF4E8"
  },
  {
    "id": 140,
    "theme": "平靜流域",
    "title": "讓心安住在寧靜中",
    "content": "平靜不是沒有風浪，而是學會與之共處。",
    "question": "此刻什麼能讓我感到平靜？",
    "breath": "calm",
    "color": "#E8F4F8"
  },
  {
    "id": 141,
    "theme": "行動流域",
    "title": "小步前進也是進步",
    "content": "前進比完美更重要。",
    "question": "完成這件事會帶給我什麼？",
    "breath": "energize",
    "color": "#FFE8D6"
  },
  {
    "id": 142,
    "theme": "共感流域",
    "title": "允許自己被理解",
    "content": "同在就是支持。",
    "question": "我想被誰理解？我準備好了嗎？",
    "breath": "gentle",
    "color": "#D8E3E8"
  },
  {
    "id": 143,
    "theme": "修復流域",
    "title": "修復是一種智慧",
    "content": "情緒需要被感受而非壓抑。",
    "question": "此刻我的身體想告訴我什麼？",
    "breath": "restore",
    "color": "#E8F4E8"
  },
  {
    "id": 144,
    "theme": "接納流域",
    "title": "不完美也值得被愛",
    "content": "每個部分都有存在的意義。",
    "question": "我能接納自己的哪個部分？",
    "breath": "gentle",
    "color": "#F0E8F4"
  },
  {
    "id": 145,
    "theme": "專注流域",
    "title": "一次只做一件事",
    "content": "此刻就是全部。",
    "question": "此刻我的感受是什麼？",
    "breath": "focus",
    "color": "#E8F0F8"
  },
  {
    "id": 146,
    "theme": "希望流域",
    "title": "每天都是新開始",
    "content": "困境是暫時的。",
    "question": "什麼讓我感到有希望？",
    "breath": "hope",
    "color": "#FFF4E8"
  },
  {
    "id": 147,
    "theme": "平靜流域",
    "title": "在風暴中心",
    "content": "放下才能平靜。",
    "question": "此刻什麼能讓我感到平靜？",
    "breath": "calm",
    "color": "#E8F4F8"
  },
  {
    "id": 148,
    "theme": "行動流域",
    "title": "小步前進也是進步",
    "content": "行動帶來清晰。",
    "question": "什麼阻止了我開始？",
    "breath": "energize",
    "color": "#FFE8D6"
  },
  {
    "id": 149,
    "theme": "共感流域",
    "title": "同理心的力量",
    "content": "聆聽比建議更重要。",
    "question": "此刻我需要什麼樣的陪伴？",
    "breath": "gentle",
    "color": "#D8E3E8"
  },
  {
    "id": 150,
    "theme": "修復流域",
    "title": "身心需要休息",
    "content": "修復是持續的過程。",
    "question": "什麼能讓我感到被照顧？",
    "breath": "restore",
    "color": "#E8F4E8"
  },
  {
    "id": 151,
    "theme": "接納流域",
    "title": "允許不完美存在",
    "content": "接納帶來自由。",
    "question": "什麼讓我覺得自己不夠好？",
    "breath": "gentle",
    "color": "#F0E8F4"
  },
  {
    "id": 152,
    "theme": "專注流域",
    "title": "放下過去與未來",
    "content": "此刻就是全部。",
    "question": "此刻我的感受是什麼？",
    "breath": "focus",
    "color": "#E8F0F8"
  },
  {
    "id": 153,
    "theme": "希望流域",
    "title": "相信改變的力量",
    "content": "相信總會好轉。",
    "question": "我想創造什麼樣的未來？",
    "breath": "hope",
    "color": "#FFF4E8"
  },
  {
    "id": 154,
    "theme": "平靜流域",
    "title": "內在的平靜",
    "content": "放下才能平靜。",
    "question": "如何在不確定中找到安定？",
    "breath": "calm",
    "color": "#E8F4F8"
  },
  {
    "id": 155,
    "theme": "行動流域",
    "title": "行動創造可能",
    "content": "一步步靠近理想。",
    "question": "什麼阻止了我開始？",
    "breath": "energize",
    "color": "#FFE8D6"
  },
  {
    "id": 156,
    "theme": "共感流域",
    "title": "真誠的對話",
    "content": "同在就是支持。",
    "question": "此刻我需要什麼樣的陪伴？",
    "breath": "gentle",
    "color": "#D8E3E8"
  },
  {
    "id": 157,
    "theme": "修復流域",
    "title": "接受情緒的起伏",
    "content": "休息是為了走更長的路。",
    "question": "此刻我需要如何被理解，才能感覺安心？",
    "breath": "restore",
    "color": "#E8F4E8"
  },
  {
    "id": 158,
    "theme": "接納流域",
    "title": "放下自我批判",
    "content": "完整包含光明與陰影。",
    "question": "如果接納自己，會發生什麼？",
    "breath": "gentle",
    "color": "#F0E8F4"
  },
  {
    "id": 159,
    "theme": "專注流域",
    "title": "臨在的力量",
    "content": "活在當下減少焦慮。",
    "question": "我在擔心什麼還未發生的事？",
    "breath": "focus",
    "color": "#E8F0F8"
  },
  {
    "id": 160,
    "theme": "希望流域",
    "title": "黎明前的黑暗",
    "content": "希望讓我們繼續前行。",
    "question": "我想創造什麼樣的未來？",
    "breath": "hope",
    "color": "#FFF4E8"
  },
  {
    "id": 161,
    "theme": "平靜流域",
    "title": "寧靜是答案",
    "content": "平靜不是沒有風浪，而是學會與之共處。",
    "question": "我在抗拒什麼？",
    "breath": "calm",
    "color": "#E8F4F8"
  },
  {
    "id": 162,
    "theme": "行動流域",
    "title": "踏出第一步",
    "content": "每個行動都是改變的種子。",
    "question": "此刻我可以採取哪個最小的行動？",
    "breath": "energize",
    "color": "#FFE8D6"
  },
  {
    "id": 163,
    "theme": "共感流域",
    "title": "脆弱是勇氣",
    "content": "聆聽比建議更重要。",
    "question": "我想被誰理解？我準備好了嗎？",
    "breath": "gentle",
    "color": "#D8E3E8"
  },
  {
    "id": 164,
    "theme": "修復流域",
    "title": "溫柔對待自己",
    "content": "情緒需要被感受而非壓抑。",
    "question": "此刻我需要如何被理解，才能感覺安心？",
    "breath": "restore",
    "color": "#E8F4E8"
  },
  {
    "id": 165,
    "theme": "接納流域",
    "title": "這樣的我也很好",
    "content": "完整包含光明與陰影。",
    "question": "我能接納自己的哪個部分？",
    "breath": "gentle",
    "color": "#F0E8F4"
  },
  {
    "id": 166,
    "theme": "專注流域",
    "title": "覺察此時此刻",
    "content": "專注創造品質。",
    "question": "如何將注意力帶回此刻？",
    "breath": "focus",
    "color": "#E8F0F8"
  },
  {
    "id": 167,
    "theme": "希望流域",
    "title": "相信美好會到來",
    "content": "希望讓我們繼續前行。",
    "question": "什麼讓我感到有希望？",
    "breath": "hope",
    "color": "#FFF4E8"
  },
  {
    "id": 168,
    "theme": "平靜流域",
    "title": "內在的平靜",
    "content": "平靜是一種選擇。",
    "question": "此刻什麼能讓我感到平靜？",
    "breath": "calm",
    "color": "#E8F4F8"
  },
  {
    "id": 169,
    "theme": "行動流域",
    "title": "行動創造可能",
    "content": "前進比完美更重要。",
    "question": "此刻我可以採取哪個最小的行動？",
    "breath": "energize",
    "color": "#FFE8D6"
  },
  {
    "id": 170,
    "theme": "共感流域",
    "title": "真誠的對話",
    "content": "真實的自己值得被愛。",
    "question": "我能如何更真誠地表達？",
    "breath": "gentle",
    "color": "#D8E3E8"
  },
  {
    "id": 171,
    "theme": "修復流域",
    "title": "先陪自己安靜片刻",
    "content": "修復是持續的過程。",
    "question": "什麼能讓我感到被照顧？",
    "breath": "restore",
    "color": "#E8F4E8"
  },
  {
    "id": 172,
    "theme": "接納流域",
    "title": "擁抱真實的自己",
    "content": "接納是成長的開始。",
    "question": "什麼讓我覺得自己不夠好？",
    "breath": "gentle",
    "color": "#F0E8F4"
  },
  {
    "id": 173,
    "theme": "專注流域",
    "title": "覺察此時此刻",
    "content": "此刻就是全部。",
    "question": "如何將注意力帶回此刻？",
    "breath": "focus",
    "color": "#E8F0F8"
  },
  {
    "id": 174,
    "theme": "希望流域",
    "title": "困難終會過去",
    "content": "困境是暫時的。",
    "question": "我想創造什麼樣的未來？",
    "breath": "hope",
    "color": "#FFF4E8"
  },
  {
    "id": 175,
    "theme": "平靜流域",
    "title": "在混亂中保持平靜",
    "content": "平靜不是沒有風浪，而是學會與之共處。",
    "question": "如何在不確定中找到安定？",
    "breath": "calm",
    "color": "#E8F4F8"
  },
  {
    "id": 176,
    "theme": "行動流域",
    "title": "從一個小決定開始",
    "content": "行動帶來清晰。",
    "question": "完成這件事會帶給我什麼？",
    "breath": "energize",
    "color": "#FFE8D6"
  },
  {
    "id": 177,
    "theme": "共感流域",
    "title": "被看見被接住",
    "content": "聆聽比建議更重要。",
    "question": "我能如何更真誠地表達？",
    "breath": "gentle",
    "color": "#D8E3E8"
  },
  {
    "id": 178,
    "theme": "修復流域",
    "title": "修復是一種智慧",
    "content": "情緒需要被感受而非壓抑。",
    "question": "什麼能讓我感到被照顧？",
    "breath": "restore",
    "color": "#E8F4E8"
  },
  {
    "id": 179,
    "theme": "接納流域",
    "title": "接納全部的自己",
    "content": "接納是成長的開始。",
    "question": "如果接納自己，會發生什麼？",
    "breath": "gentle",
    "color": "#F0E8F4"
  },
  {
    "id": 180,
    "theme": "專注流域",
    "title": "一次只做一件事",
    "content": "專注創造品質。",
    "question": "此刻我的感受是什麼？",
    "breath": "focus",
    "color": "#E8F0F8"
  },
  {
    "id": 181,
    "theme": "希望流域",
    "title": "希望是光",
    "content": "困境是暫時的。",
    "question": "我對未來抱持什麼樣的期待？",
    "breath": "hope",
    "color": "#FFF4E8"
  },
  {
    "id": 182,
    "theme": "平靜流域",
    "title": "在風暴中心",
    "content": "平靜不是沒有風浪，而是學會與之共處。",
    "question": "如何在不確定中找到安定？",
    "breath": "calm",
    "color": "#E8F4F8"
  },
  {
    "id": 183,
    "theme": "行動流域",
    "title": "行動創造可能",
    "content": "前進比完美更重要。",
    "question": "此刻我可以採取哪個最小的行動？",
    "breath": "energize",
    "color": "#FFE8D6"
  },
  {
    "id": 184,
    "theme": "共感流域",
    "title": "允許自己被理解",
    "content": "聆聽比建議更重要。",
    "question": "我能如何更真誠地表達？",
    "breath": "gentle",
    "color": "#D8E3E8"
  },
  {
    "id": 185,
    "theme": "修復流域",
    "title": "給自己一點修復的時間",
    "content": "再向外分享溫柔與在意。",
    "question": "此刻我的身體想告訴我什麼？",
    "breath": "restore",
    "color": "#E8F4E8"
  },
  {
    "id": 186,
    "theme": "接納流域",
    "title": "放下自我批判",
    "content": "不完美的自己，也值得被愛。",
    "question": "如果接納自己，會發生什麼？",
    "breath": "gentle",
    "color": "#F0E8F4"
  },
  {
    "id": 187,
    "theme": "專注流域",
    "title": "當下是唯一真實",
    "content": "專注帶來清明。",
    "question": "此刻我的感受是什麼？",
    "breath": "focus",
    "color": "#E8F0F8"
  },
  {
    "id": 188,
    "theme": "希望流域",
    "title": "相信改變的力量",
    "content": "可能性永遠存在。",
    "question": "我想創造什麼樣的未來？",
    "breath": "hope",
    "color": "#FFF4E8"
  },
  {
    "id": 189,
    "theme": "平靜流域",
    "title": "在混亂中保持平靜",
    "content": "接受帶來安定。",
    "question": "此刻什麼能讓我感到平靜？",
    "breath": "calm",
    "color": "#E8F4F8"
  },
  {
    "id": 190,
    "theme": "行動流域",
    "title": "勇敢嘗試新事物",
    "content": "行動帶來清晰。",
    "question": "此刻我可以採取哪個最小的行動？",
    "breath": "energize",
    "color": "#FFE8D6"
  },
  {
    "id": 191,
    "theme": "共感流域",
    "title": "在關係中成長",
    "content": "同在就是支持。",
    "question": "此刻我需要什麼樣的陪伴？",
    "breath": "gentle",
    "color": "#D8E3E8"
  },
  {
    "id": 192,
    "theme": "修復流域",
    "title": "溫柔對待自己",
    "content": "再向外分享溫柔與在意。",
    "question": "什麼能讓我感到被照顧？",
    "breath": "restore",
    "color": "#E8F4E8"
  },
  {
    "id": 193,
    "theme": "接納流域",
    "title": "放下自我批判",
    "content": "不完美的自己，也值得被愛。",
    "question": "我能接納自己的哪個部分？",
    "breath": "gentle",
    "color": "#F0E8F4"
  },
  {
    "id": 194,
    "theme": "專注流域",
    "title": "回到此刻的呼吸",
    "content": "專注創造品質。",
    "question": "我在擔心什麼還未發生的事？",
    "breath": "focus",
    "color": "#E8F0F8"
  },
  {
    "id": 195,
    "theme": "希望流域",
    "title": "困難終會過去",
    "content": "每個今天都是新的開始。",
    "question": "什麼讓我感到有希望？",
    "breath": "hope",
    "color": "#FFF4E8"
  },
  {
    "id": 196,
    "theme": "平靜流域",
    "title": "在風暴中心",
    "content": "平靜是一種選擇。",
    "question": "我在抗拒什麼？",
    "breath": "calm",
    "color": "#E8F4F8"
  },
  {
    "id": 197,
    "theme": "行動流域",
    "title": "小步前進也是進步",
    "content": "前進比完美更重要。",
    "question": "此刻我可以採取哪個最小的行動？",
    "breath": "energize",
    "color": "#FFE8D6"
  },
  {
    "id": 198,
    "theme": "共感流域",
    "title": "同理心的力量",
    "content": "聆聽比建議更重要。",
    "question": "我想被誰理解？我準備好了嗎？",
    "breath": "gentle",
    "color": "#D8E3E8"
  },
  {
    "id": 199,
    "theme": "修復流域",
    "title": "溫柔對待自己",
    "content": "療癒不需要完美，只需要開始。",
    "question": "此刻我需要如何被理解，才能感覺安心？",
    "breath": "restore",
    "color": "#E8F4E8"
  },
  {
    "id": 200,
    "theme": "接納流域",
    "title": "擁抱真實的自己",
    "content": "接納帶來自由。",
    "question": "什麼讓我覺得自己不夠好？",
    "breath": "gentle",
    "color": "#F0E8F4"
  },
  {
    "id": 201,
    "theme": "專注流域",
    "title": "覺察此時此刻",
    "content": "專注創造品質。",
    "question": "如何將注意力帶回此刻？",
    "breath": "focus",
    "color": "#E8F0F8"
  },
  {
    "id": 202,
    "theme": "希望流域",
    "title": "黎明前的黑暗",
    "content": "每個今天都是新的開始。",
    "question": "什麼讓我感到有希望？",
    "breath": "hope",
    "color": "#FFF4E8"
  },
  {
    "id": 203,
    "theme": "平靜流域",
    "title": "平靜來自接納",
    "content": "平靜是一種選擇。",
    "question": "此刻什麼能讓我感到平靜？",
    "breath": "calm",
    "color": "#E8F4F8"
  },
  {
    "id": 204,
    "theme": "行動流域",
    "title": "現在就是最好的時機",
    "content": "開始永遠不會太遲。",
    "question": "完成這件事會帶給我什麼？",
    "breath": "energize",
    "color": "#FFE8D6"
  },
  {
    "id": 205,
    "theme": "共感流域",
    "title": "理解彼此的差異",
    "content": "表達需要也需要勇氣。",
    "question": "此刻我需要什麼樣的陪伴？",
    "breath": "gentle",
    "color": "#D8E3E8"
  },
  {
    "id": 206,
    "theme": "修復流域",
    "title": "修復是一種智慧",
    "content": "給自己時間復原。",
    "question": "什麼能讓我感到被照顧？",
    "breath": "restore",
    "color": "#E8F4E8"
  },
  {
    "id": 207,
    "theme": "接納流域",
    "title": "這樣的我也很好",
    "content": "你已經夠好了。",
    "question": "什麼讓我覺得自己不夠好？",
    "breath": "gentle",
    "color": "#F0E8F4"
  },
  {
    "id": 208,
    "theme": "專注流域",
    "title": "臨在的力量",
    "content": "專注帶來清明。",
    "question": "此刻我的感受是什麼？",
    "breath": "focus",
    "color": "#E8F0F8"
  },
  {
    "id": 209,
    "theme": "希望流域",
    "title": "黎明前的黑暗",
    "content": "困境是暫時的。",
    "question": "我對未來抱持什麼樣的期待？",
    "breath": "hope",
    "color": "#FFF4E8"
  },
  {
    "id": 210,
    "theme": "平靜流域",
    "title": "在混亂中保持平靜",
    "content": "接受帶來安定。",
    "question": "如何在不確定中找到安定？",
    "breath": "calm",
    "color": "#E8F4F8"
  },
  {
    "id": 211,
    "theme": "行動流域",
    "title": "相信行動的力量",
    "content": "開始永遠不會太遲。",
    "question": "此刻我可以採取哪個最小的行動？",
    "breath": "energize",
    "color": "#FFE8D6"
  },
  {
    "id": 212,
    "theme": "共感流域",
    "title": "脆弱是勇氣",
    "content": "理解不需要相同。",
    "question": "我想被誰理解？我準備好了嗎？",
    "breath": "gentle",
    "color": "#D8E3E8"
  },
  {
    "id": 213,
    "theme": "修復流域",
    "title": "先陪自己安靜片刻",
    "content": "療癒不需要完美，只需要開始。",
    "question": "什麼能讓我感到被照顧？",
    "breath": "restore",
    "color": "#E8F4E8"
  },
  {
    "id": 214,
    "theme": "接納流域",
    "title": "放下自我批判",
    "content": "完整包含光明與陰影。",
    "question": "什麼讓我覺得自己不夠好？",
    "breath": "gentle",
    "color": "#F0E8F4"
  },
  {
    "id": 215,
    "theme": "專注流域",
    "title": "一次只做一件事",
    "content": "此刻就是全部。",
    "question": "此刻我的感受是什麼？",
    "breath": "focus",
    "color": "#E8F0F8"
  },
  {
    "id": 216,
    "theme": "希望流域",
    "title": "保持期待",
    "content": "希望讓我們繼續前行。",
    "question": "什麼讓我感到有希望？",
    "breath": "hope",
    "color": "#FFF4E8"
  },
  {
    "id": 217,
    "theme": "平靜流域",
    "title": "內在的平靜",
    "content": "平靜不是沒有風浪，而是學會與之共處。",
    "question": "如何在不確定中找到安定？",
    "breath": "calm",
    "color": "#E8F4F8"
  },
  {
    "id": 218,
    "theme": "行動流域",
    "title": "勇敢嘗試新事物",
    "content": "行動帶來清晰。",
    "question": "什麼阻止了我開始？",
    "breath": "energize",
    "color": "#FFE8D6"
  },
  {
    "id": 219,
    "theme": "共感流域",
    "title": "在關係中成長",
    "content": "脆弱是連結的開始。",
    "question": "此刻我需要什麼樣的陪伴？",
    "breath": "gentle",
    "color": "#D8E3E8"
  },
  {
    "id": 220,
    "theme": "修復流域",
    "title": "先陪自己安靜片刻",
    "content": "給自己時間復原。",
    "question": "此刻我需要如何被理解，才能感覺安心？",
    "breath": "restore",
    "color": "#E8F4E8"
  },
  {
    "id": 221,
    "theme": "接納流域",
    "title": "擁抱真實的自己",
    "content": "每個部分都有存在的意義。",
    "question": "什麼讓我覺得自己不夠好？",
    "breath": "gentle",
    "color": "#F0E8F4"
  },
  {
    "id": 222,
    "theme": "專注流域",
    "title": "放下過去與未來",
    "content": "當下是唯一真實存在的時刻。",
    "question": "此刻我的感受是什麼？",
    "breath": "focus",
    "color": "#E8F0F8"
  },
  {
    "id": 223,
    "theme": "希望流域",
    "title": "未來仍有無限可能",
    "content": "未來充滿驚喜。",
    "question": "我對未來抱持什麼樣的期待？",
    "breath": "hope",
    "color": "#FFF4E8"
  },
  {
    "id": 224,
    "theme": "平靜流域",
    "title": "在混亂中保持平靜",
    "content": "在當下找到安定。",
    "question": "我在抗拒什麼？",
    "breath": "calm",
    "color": "#E8F4F8"
  },
  {
    "id": 225,
    "theme": "行動流域",
    "title": "勇敢嘗試新事物",
    "content": "每個行動都是改變的種子。",
    "question": "完成這件事會帶給我什麼？",
    "breath": "energize",
    "color": "#FFE8D6"
  },
  {
    "id": 226,
    "theme": "共感流域",
    "title": "真誠的對話",
    "content": "同在就是支持。",
    "question": "我想被誰理解？我準備好了嗎？",
    "breath": "gentle",
    "color": "#D8E3E8"
  },
  {
    "id": 227,
    "theme": "修復流域",
    "title": "療癒需要耐心",
    "content": "再向外分享溫柔與在意。",
    "question": "此刻我的身體想告訴我什麼？",
    "breath": "restore",
    "color": "#E8F4E8"
  },
  {
    "id": 228,
    "theme": "接納流域",
    "title": "自我接納是力量",
    "content": "接納帶來自由。",
    "question": "什麼讓我覺得自己不夠好？",
    "breath": "gentle",
    "color": "#F0E8F4"
  },
  {
    "id": 229,
    "theme": "專注流域",
    "title": "一次只做一件事",
    "content": "活在當下減少焦慮。",
    "question": "如何將注意力帶回此刻？",
    "breath": "focus",
    "color": "#E8F0F8"
  },
  {
    "id": 230,
    "theme": "希望流域",
    "title": "相信美好會到來",
    "content": "可能性永遠存在。",
    "question": "我想創造什麼樣的未來？",
    "breath": "hope",
    "color": "#FFF4E8"
  },
  {
    "id": 231,
    "theme": "平靜流域",
    "title": "在混亂中保持平靜",
    "content": "接受帶來安定。",
    "question": "此刻什麼能讓我感到平靜？",
    "breath": "calm",
    "color": "#E8F4F8"
  },
  {
    "id": 232,
    "theme": "行動流域",
    "title": "踏出第一步",
    "content": "從小事開始改變。",
    "question": "此刻我可以採取哪個最小的行動？",
    "breath": "energize",
    "color": "#FFE8D6"
  },
  {
    "id": 233,
    "theme": "共感流域",
    "title": "脆弱是勇氣",
    "content": "聆聽比建議更重要。",
    "question": "我能如何更真誠地表達？",
    "breath": "gentle",
    "color": "#D8E3E8"
  },
  {
    "id": 234,
    "theme": "修復流域",
    "title": "修復是一種智慧",
    "content": "修復是持續的過程。",
    "question": "此刻我需要如何被理解，才能感覺安心？",
    "breath": "restore",
    "color": "#E8F4E8"
  },
  {
    "id": 235,
    "theme": "接納流域",
    "title": "不完美也值得被愛",
    "content": "完整包含光明與陰影。",
    "question": "我能接納自己的哪個部分？",
    "breath": "gentle",
    "color": "#F0E8F4"
  },
  {
    "id": 236,
    "theme": "專注流域",
    "title": "一次只做一件事",
    "content": "活在當下減少焦慮。",
    "question": "如何將注意力帶回此刻？",
    "breath": "focus",
    "color": "#E8F0F8"
  },
  {
    "id": 237,
    "theme": "希望流域",
    "title": "黎明前的黑暗",
    "content": "每個今天都是新的開始。",
    "question": "我對未來抱持什麼樣的期待？",
    "breath": "hope",
    "color": "#FFF4E8"
  },
  {
    "id": 238,
    "theme": "平靜流域",
    "title": "在風暴中心",
    "content": "在當下找到安定。",
    "question": "如何在不確定中找到安定？",
    "breath": "calm",
    "color": "#E8F4F8"
  },
  {
    "id": 239,
    "theme": "行動流域",
    "title": "踏出第一步",
    "content": "一步步靠近理想。",
    "question": "此刻我可以採取哪個最小的行動？",
    "breath": "energize",
    "color": "#FFE8D6"
  },
  {
    "id": 240,
    "theme": "共感流域",
    "title": "真誠的對話",
    "content": "理解不需要相同。",
    "question": "我能如何更真誠地表達？",
    "breath": "gentle",
    "color": "#D8E3E8"
  },
  {
    "id": 241,
    "theme": "修復流域",
    "title": "溫柔對待自己",
    "content": "休息是為了走更長的路。",
    "question": "什麼能讓我感到被照顧？",
    "breath": "restore",
    "color": "#E8F4E8"
  },
  {
    "id": 242,
    "theme": "接納流域",
    "title": "放下自我批判",
    "content": "每個部分都有存在的意義。",
    "question": "如果接納自己，會發生什麼？",
    "breath": "gentle",
    "color": "#F0E8F4"
  },
  {
    "id": 243,
    "theme": "專注流域",
    "title": "覺察此時此刻",
    "content": "覺察就是力量。",
    "question": "我在擔心什麼還未發生的事？",
    "breath": "focus",
    "color": "#E8F0F8"
  },
  {
    "id": 244,
    "theme": "希望流域",
    "title": "相信美好會到來",
    "content": "每個今天都是新的開始。",
    "question": "什麼讓我感到有希望？",
    "breath": "hope",
    "color": "#FFF4E8"
  },
  {
    "id": 245,
    "theme": "平靜流域",
    "title": "接受不確定",
    "content": "平靜是一種選擇。",
    "question": "我在抗拒什麼？",
    "breath": "calm",
    "color": "#E8F4F8"
  },
  {
    "id": 246,
    "theme": "行動流域",
    "title": "相信行動的力量",
    "content": "前進比完美更重要。",
    "question": "完成這件事會帶給我什麼？",
    "breath": "energize",
    "color": "#FFE8D6"
  },
  {
    "id": 247,
    "theme": "共感流域",
    "title": "在關係中成長",
    "content": "同在就是支持。",
    "question": "此刻我需要什麼樣的陪伴？",
    "breath": "gentle",
    "color": "#D8E3E8"
  },
  {
    "id": 248,
    "theme": "修復流域",
    "title": "身心需要休息",
    "content": "再向外分享溫柔與在意。",
    "question": "什麼能讓我感到被照顧？",
    "breath": "restore",
    "color": "#E8F4E8"
  },
  {
    "id": 249,
    "theme": "接納流域",
    "title": "放下自我批判",
    "content": "接納帶來自由。",
    "question": "如果接納自己，會發生什麼？",
    "breath": "gentle",
    "color": "#F0E8F4"
  },
  {
    "id": 250,
    "theme": "專注流域",
    "title": "覺察此時此刻",
    "content": "當下是唯一真實存在的時刻。",
    "question": "此刻我的感受是什麼？",
    "breath": "focus",
    "color": "#E8F0F8"
  },
  {
    "id": 251,
    "theme": "希望流域",
    "title": "相信改變的力量",
    "content": "困境是暫時的。",
    "question": "什麼讓我感到有希望？",
    "breath": "hope",
    "color": "#FFF4E8"
  },
  {
    "id": 252,
    "theme": "平靜流域",
    "title": "在混亂中保持平靜",
    "content": "在當下找到安定。",
    "question": "我在抗拒什麼？",
    "breath": "calm",
    "color": "#E8F4F8"
  },
  {
    "id": 253,
    "theme": "行動流域",
    "title": "從一個小決定開始",
    "content": "每個行動都是改變的種子。",
    "question": "此刻我可以採取哪個最小的行動？",
    "breath": "energize",
    "color": "#FFE8D6"
  },
  {
    "id": 254,
    "theme": "共感流域",
    "title": "脆弱是勇氣",
    "content": "真實的自己值得被愛。",
    "question": "我想被誰理解？我準備好了嗎？",
    "breath": "gentle",
    "color": "#D8E3E8"
  },
  {
    "id": 255,
    "theme": "修復流域",
    "title": "接受情緒的起伏",
    "content": "療癒不需要完美，只需要開始。",
    "question": "什麼能讓我感到被照顧？",
    "breath": "restore",
    "color": "#E8F4E8"
  },
  {
    "id": 256,
    "theme": "接納流域",
    "title": "接納全部的自己",
    "content": "完整包含光明與陰影。",
    "question": "如果接納自己，會發生什麼？",
    "breath": "gentle",
    "color": "#F0E8F4"
  },
  {
    "id": 257,
    "theme": "專注流域",
    "title": "臨在的力量",
    "content": "專注創造品質。",
    "question": "我在擔心什麼還未發生的事？",
    "breath": "focus",
    "color": "#E8F0F8"
  },
  {
    "id": 258,
    "theme": "希望流域",
    "title": "相信改變的力量",
    "content": "相信總會好轉。",
    "question": "我想創造什麼樣的未來？",
    "breath": "hope",
    "color": "#FFF4E8"
  },
  {
    "id": 259,
    "theme": "平靜流域",
    "title": "在風暴中心",
    "content": "放下才能平靜。",
    "question": "我在抗拒什麼？",
    "breath": "calm",
    "color": "#E8F4F8"
  },
  {
    "id": 260,
    "theme": "行動流域",
    "title": "現在就是最好的時機",
    "content": "開始永遠不會太遲。",
    "question": "什麼阻止了我開始？",
    "breath": "energize",
    "color": "#FFE8D6"
  },
  {
    "id": 261,
    "theme": "共感流域",
    "title": "脆弱是勇氣",
    "content": "脆弱是連結的開始。",
    "question": "此刻我需要什麼樣的陪伴？",
    "breath": "gentle",
    "color": "#D8E3E8"
  },
  {
    "id": 262,
    "theme": "修復流域",
    "title": "溫柔對待自己",
    "content": "給自己時間復原。",
    "question": "此刻我的身體想告訴我什麼？",
    "breath": "restore",
    "color": "#E8F4E8"
  },
  {
    "id": 263,
    "theme": "接納流域",
    "title": "擁抱真實的自己",
    "content": "你已經夠好了。",
    "question": "什麼讓我覺得自己不夠好？",
    "breath": "gentle",
    "color": "#F0E8F4"
  },
  {
    "id": 264,
    "theme": "專注流域",
    "title": "回到此刻的呼吸",
    "content": "此刻就是全部。",
    "question": "此刻我的感受是什麼？",
    "breath": "focus",
    "color": "#E8F0F8"
  },
  {
    "id": 265,
    "theme": "希望流域",
    "title": "每天都是新開始",
    "content": "相信總會好轉。",
    "question": "我對未來抱持什麼樣的期待？",
    "breath": "hope",
    "color": "#FFF4E8"
  },
  {
    "id": 266,
    "theme": "平靜流域",
    "title": "在風暴中心",
    "content": "平靜是一種選擇。",
    "question": "此刻什麼能讓我感到平靜？",
    "breath": "calm",
    "color": "#E8F4F8"
  },
  {
    "id": 267,
    "theme": "行動流域",
    "title": "打破拖延的循環",
    "content": "開始永遠不會太遲。",
    "question": "什麼阻止了我開始？",
    "breath": "energize",
    "color": "#FFE8D6"
  },
  {
    "id": 268,
    "theme": "共感流域",
    "title": "在關係中成長",
    "content": "脆弱是連結的開始。",
    "question": "此刻我需要什麼樣的陪伴？",
    "breath": "gentle",
    "color": "#D8E3E8"
  },
  {
    "id": 269,
    "theme": "修復流域",
    "title": "給自己一點修復的時間",
    "content": "給自己時間復原。",
    "question": "什麼能讓我感到被照顧？",
    "breath": "restore",
    "color": "#E8F4E8"
  },
  {
    "id": 270,
    "theme": "接納流域",
    "title": "允許不完美存在",
    "content": "每個部分都有存在的意義。",
    "question": "如果接納自己，會發生什麼？",
    "breath": "gentle",
    "color": "#F0E8F4"
  },
  {
    "id": 271,
    "theme": "專注流域",
    "title": "覺察此時此刻",
    "content": "覺察就是力量。",
    "question": "如何將注意力帶回此刻？",
    "breath": "focus",
    "color": "#E8F0F8"
  },
  {
    "id": 272,
    "theme": "希望流域",
    "title": "保持期待",
    "content": "困境是暫時的。",
    "question": "我對未來抱持什麼樣的期待？",
    "breath": "hope",
    "color": "#FFF4E8"
  },
  {
    "id": 273,
    "theme": "平靜流域",
    "title": "接受不確定",
    "content": "寧靜來自內在。",
    "question": "此刻什麼能讓我感到平靜？",
    "breath": "calm",
    "color": "#E8F4F8"
  },
  {
    "id": 274,
    "theme": "行動流域",
    "title": "相信行動的力量",
    "content": "一步步靠近理想。",
    "question": "什麼阻止了我開始？",
    "breath": "energize",
    "color": "#FFE8D6"
  },
  {
    "id": 275,
    "theme": "共感流域",
    "title": "連結從聆聽開始",
    "content": "同在就是支持。",
    "question": "我想被誰理解？我準備好了嗎？",
    "breath": "gentle",
    "color": "#D8E3E8"
  },
  {
    "id": 276,
    "theme": "修復流域",
    "title": "身心需要休息",
    "content": "情緒需要被感受而非壓抑。",
    "question": "什麼能讓我感到被照顧？",
    "breath": "restore",
    "color": "#E8F4E8"
  },
  {
    "id": 277,
    "theme": "接納流域",
    "title": "善待內在小孩",
    "content": "不完美的自己，也值得被愛。",
    "question": "我能接納自己的哪個部分？",
    "breath": "gentle",
    "color": "#F0E8F4"
  },
  {
    "id": 278,
    "theme": "專注流域",
    "title": "活在當下",
    "content": "此刻就是全部。",
    "question": "此刻我的感受是什麼？",
    "breath": "focus",
    "color": "#E8F0F8"
  },
  {
    "id": 279,
    "theme": "希望流域",
    "title": "困難終會過去",
    "content": "未來充滿驚喜。",
    "question": "什麼讓我感到有希望？",
    "breath": "hope",
    "color": "#FFF4E8"
  },
  {
    "id": 280,
    "theme": "平靜流域",
    "title": "內在的平靜",
    "content": "在當下找到安定。",
    "question": "我在抗拒什麼？",
    "breath": "calm",
    "color": "#E8F4F8"
  },
  {
    "id": 281,
    "theme": "行動流域",
    "title": "相信行動的力量",
    "content": "從小事開始改變。",
    "question": "此刻我可以採取哪個最小的行動？",
    "breath": "energize",
    "color": "#FFE8D6"
  },
  {
    "id": 282,
    "theme": "共感流域",
    "title": "理解彼此的差異",
    "content": "理解不需要相同。",
    "question": "我想被誰理解？我準備好了嗎？",
    "breath": "gentle",
    "color": "#D8E3E8"
  },
  {
    "id": 283,
    "theme": "修復流域",
    "title": "接受情緒的起伏",
    "content": "情緒需要被感受而非壓抑。",
    "question": "此刻我需要如何被理解，才能感覺安心？",
    "breath": "restore",
    "color": "#E8F4E8"
  },
  {
    "id": 284,
    "theme": "接納流域",
    "title": "擁抱真實的自己",
    "content": "你已經夠好了。",
    "question": "我能接納自己的哪個部分？",
    "breath": "gentle",
    "color": "#F0E8F4"
  },
  {
    "id": 285,
    "theme": "專注流域",
    "title": "覺察此時此刻",
    "content": "活在當下減少焦慮。",
    "question": "我在擔心什麼還未發生的事？",
    "breath": "focus",
    "color": "#E8F0F8"
  },
  {
    "id": 286,
    "theme": "希望流域",
    "title": "困難終會過去",
    "content": "困境是暫時的。",
    "question": "我想創造什麼樣的未來？",
    "breath": "hope",
    "color": "#FFF4E8"
  },
  {
    "id": 287,
    "theme": "平靜流域",
    "title": "寧靜是答案",
    "content": "平靜是一種選擇。",
    "question": "此刻什麼能讓我感到平靜？",
    "breath": "calm",
    "color": "#E8F4F8"
  },
  {
    "id": 288,
    "theme": "行動流域",
    "title": "小步前進也是進步",
    "content": "行動帶來清晰。",
    "question": "此刻我可以採取哪個最小的行動？",
    "breath": "energize",
    "color": "#FFE8D6"
  },
  {
    "id": 289,
    "theme": "共感流域",
    "title": "在關係中成長",
    "content": "脆弱是連結的開始。",
    "question": "我想被誰理解？我準備好了嗎？",
    "breath": "gentle",
    "color": "#D8E3E8"
  },
  {
    "id": 290,
    "theme": "修復流域",
    "title": "接受情緒的起伏",
    "content": "情緒需要被感受而非壓抑。",
    "question": "此刻我的身體想告訴我什麼？",
    "breath": "restore",
    "color": "#E8F4E8"
  },
  {
    "id": 291,
    "theme": "接納流域",
    "title": "放下自我批判",
    "content": "接納帶來自由。",
    "question": "什麼讓我覺得自己不夠好？",
    "breath": "gentle",
    "color": "#F0E8F4"
  },
  {
    "id": 292,
    "theme": "專注流域",
    "title": "覺察此時此刻",
    "content": "覺察就是力量。",
    "question": "此刻我的感受是什麼？",
    "breath": "focus",
    "color": "#E8F0F8"
  },
  {
    "id": 293,
    "theme": "希望流域",
    "title": "保持期待",
    "content": "困境是暫時的。",
    "question": "我想創造什麼樣的未來？",
    "breath": "hope",
    "color": "#FFF4E8"
  },
  {
    "id": 294,
    "theme": "平靜流域",
    "title": "平靜來自接納",
    "content": "接受帶來安定。",
    "question": "如何在不確定中找到安定？",
    "breath": "calm",
    "color": "#E8F4F8"
  },
  {
    "id": 295,
    "theme": "行動流域",
    "title": "從一個小決定開始",
    "content": "每個行動都是改變的種子。",
    "question": "什麼阻止了我開始？",
    "breath": "energize",
    "color": "#FFE8D6"
  },
  {
    "id": 296,
    "theme": "共感流域",
    "title": "真誠的對話",
    "content": "脆弱是連結的開始。",
    "question": "此刻我需要什麼樣的陪伴？",
    "breath": "gentle",
    "color": "#D8E3E8"
  },
  {
    "id": 297,
    "theme": "修復流域",
    "title": "溫柔對待自己",
    "content": "休息是為了走更長的路。",
    "question": "什麼能讓我感到被照顧？",
    "breath": "restore",
    "color": "#E8F4E8"
  },
  {
    "id": 298,
    "theme": "接納流域",
    "title": "接納全部的自己",
    "content": "接納是成長的開始。",
    "question": "如果接納自己，會發生什麼？",
    "breath": "gentle",
    "color": "#F0E8F4"
  },
  {
    "id": 299,
    "theme": "專注流域",
    "title": "專注於眼前",
    "content": "專注帶來清明。",
    "question": "我在擔心什麼還未發生的事？",
    "breath": "focus",
    "color": "#E8F0F8"
  },
  {
    "id": 300,
    "theme": "希望流域",
    "title": "希望是光",
    "content": "希望讓我們繼續前行。",
    "question": "我想創造什麼樣的未來？",
    "breath": "hope",
    "color": "#FFF4E8"
  },
  {
    "id": 301,
    "theme": "平靜流域",
    "title": "內在的平靜",
    "content": "平靜不是沒有風浪，而是學會與之共處。",
    "question": "此刻什麼能讓我感到平靜？",
    "breath": "calm",
    "color": "#E8F4F8"
  },
  {
    "id": 302,
    "theme": "行動流域",
    "title": "打破拖延的循環",
    "content": "一步步靠近理想。",
    "question": "完成這件事會帶給我什麼？",
    "breath": "energize",
    "color": "#FFE8D6"
  },
  {
    "id": 303,
    "theme": "共感流域",
    "title": "真誠的對話",
    "content": "聆聽比建議更重要。",
    "question": "我想被誰理解？我準備好了嗎？",
    "breath": "gentle",
    "color": "#D8E3E8"
  },
  {
    "id": 304,
    "theme": "修復流域",
    "title": "先陪自己安靜片刻",
    "content": "再向外分享溫柔與在意。",
    "question": "什麼能讓我感到被照顧？",
    "breath": "restore",
    "color": "#E8F4E8"
  },
  {
    "id": 305,
    "theme": "接納流域",
    "title": "放下自我批判",
    "content": "你已經夠好了。",
    "question": "什麼讓我覺得自己不夠好？",
    "breath": "gentle",
    "color": "#F0E8F4"
  },
  {
    "id": 306,
    "theme": "專注流域",
    "title": "覺察此時此刻",
    "content": "覺察就是力量。",
    "question": "我在擔心什麼還未發生的事？",
    "breath": "focus",
    "color": "#E8F0F8"
  },
  {
    "id": 307,
    "theme": "希望流域",
    "title": "黎明前的黑暗",
    "content": "每個今天都是新的開始。",
    "question": "什麼讓我感到有希望？",
    "breath": "hope",
    "color": "#FFF4E8"
  },
  {
    "id": 308,
    "theme": "平靜流域",
    "title": "寧靜是答案",
    "content": "在當下找到安定。",
    "question": "如何在不確定中找到安定？",
    "breath": "calm",
    "color": "#E8F4F8"
  },
  {
    "id": 309,
    "theme": "行動流域",
    "title": "打破拖延的循環",
    "content": "行動帶來清晰。",
    "question": "此刻我可以採取哪個最小的行動？",
    "breath": "energize",
    "color": "#FFE8D6"
  },
  {
    "id": 310,
    "theme": "共感流域",
    "title": "同理心的力量",
    "content": "表達需要也需要勇氣。",
    "question": "我能如何更真誠地表達？",
    "breath": "gentle",
    "color": "#D8E3E8"
  },
  {
    "id": 311,
    "theme": "修復流域",
    "title": "身心需要休息",
    "content": "給自己時間復原。",
    "question": "此刻我的身體想告訴我什麼？",
    "breath": "restore",
    "color": "#E8F4E8"
  },
  {
    "id": 312,
    "theme": "接納流域",
    "title": "允許不完美存在",
    "content": "接納帶來自由。",
    "question": "如果接納自己，會發生什麼？",
    "breath": "gentle",
    "color": "#F0E8F4"
  },
  {
    "id": 313,
    "theme": "專注流域",
    "title": "當下是唯一真實",
    "content": "當下是唯一真實存在的時刻。",
    "question": "此刻我的感受是什麼？",
    "breath": "focus",
    "color": "#E8F0F8"
  },
  {
    "id": 314,
    "theme": "希望流域",
    "title": "希望是光",
    "content": "每個今天都是新的開始。",
    "question": "我想創造什麼樣的未來？",
    "breath": "hope",
    "color": "#FFF4E8"
  },
  {
    "id": 315,
    "theme": "平靜流域",
    "title": "放下控制",
    "content": "接受帶來安定。",
    "question": "此刻什麼能讓我感到平靜？",
    "breath": "calm",
    "color": "#E8F4F8"
  },
  {
    "id": 316,
    "theme": "行動流域",
    "title": "相信行動的力量",
    "content": "前進比完美更重要。",
    "question": "完成這件事會帶給我什麼？",
    "breath": "energize",
    "color": "#FFE8D6"
  },
  {
    "id": 317,
    "theme": "共感流域",
    "title": "同理心的力量",
    "content": "表達需要也需要勇氣。",
    "question": "此刻我需要什麼樣的陪伴？",
    "breath": "gentle",
    "color": "#D8E3E8"
  },
  {
    "id": 318,
    "theme": "修復流域",
    "title": "先陪自己安靜片刻",
    "content": "休息是為了走更長的路。",
    "question": "此刻我需要如何被理解，才能感覺安心？",
    "breath": "restore",
    "color": "#E8F4E8"
  },
  {
    "id": 319,
    "theme": "接納流域",
    "title": "善待內在小孩",
    "content": "接納帶來自由。",
    "question": "什麼讓我覺得自己不夠好？",
    "breath": "gentle",
    "color": "#F0E8F4"
  },
  {
    "id": 320,
    "theme": "專注流域",
    "title": "回到此刻的呼吸",
    "content": "覺察就是力量。",
    "question": "如何將注意力帶回此刻？",
    "breath": "focus",
    "color": "#E8F0F8"
  },
  {
    "id": 321,
    "theme": "希望流域",
    "title": "相信美好會到來",
    "content": "可能性永遠存在。",
    "question": "我對未來抱持什麼樣的期待？",
    "breath": "hope",
    "color": "#FFF4E8"
  },
  {
    "id": 322,
    "theme": "平靜流域",
    "title": "平靜來自接納",
    "content": "平靜是一種選擇。",
    "question": "我在抗拒什麼？",
    "breath": "calm",
    "color": "#E8F4F8"
  },
  {
    "id": 323,
    "theme": "行動流域",
    "title": "踏出第一步",
    "content": "一步步靠近理想。",
    "question": "此刻我可以採取哪個最小的行動？",
    "breath": "energize",
    "color": "#FFE8D6"
  },
  {
    "id": 324,
    "theme": "共感流域",
    "title": "理解彼此的差異",
    "content": "同在就是支持。",
    "question": "此刻我需要什麼樣的陪伴？",
    "breath": "gentle",
    "color": "#D8E3E8"
  },
  {
    "id": 325,
    "theme": "修復流域",
    "title": "修復是一種智慧",
    "content": "情緒需要被感受而非壓抑。",
    "question": "什麼能讓我感到被照顧？",
    "breath": "restore",
    "color": "#E8F4E8"
  },
  {
    "id": 326,
    "theme": "接納流域",
    "title": "這樣的我也很好",
    "content": "每個部分都有存在的意義。",
    "question": "什麼讓我覺得自己不夠好？",
    "breath": "gentle",
    "color": "#F0E8F4"
  },
  {
    "id": 327,
    "theme": "專注流域",
    "title": "當下是唯一真實",
    "content": "活在當下減少焦慮。",
    "question": "如何將注意力帶回此刻？",
    "breath": "focus",
    "color": "#E8F0F8"
  },
  {
    "id": 328,
    "theme": "希望流域",
    "title": "相信改變的力量",
    "content": "希望讓我們繼續前行。",
    "question": "什麼讓我感到有希望？",
    "breath": "hope",
    "color": "#FFF4E8"
  },
  {
    "id": 329,
    "theme": "平靜流域",
    "title": "內在的平靜",
    "content": "接受帶來安定。",
    "question": "此刻什麼能讓我感到平靜？",
    "breath": "calm",
    "color": "#E8F4F8"
  },
  {
    "id": 330,
    "theme": "行動流域",
    "title": "相信行動的力量",
    "content": "行動帶來清晰。",
    "question": "什麼阻止了我開始？",
    "breath": "energize",
    "color": "#FFE8D6"
  },
  {
    "id": 331,
    "theme": "共感流域",
    "title": "允許自己被理解",
    "content": "理解不需要相同。",
    "question": "此刻我需要什麼樣的陪伴？",
    "breath": "gentle",
    "color": "#D8E3E8"
  },
  {
    "id": 332,
    "theme": "修復流域",
    "title": "溫柔對待自己",
    "content": "情緒需要被感受而非壓抑。",
    "question": "此刻我的身體想告訴我什麼？",
    "breath": "restore",
    "color": "#E8F4E8"
  },
  {
    "id": 333,
    "theme": "接納流域",
    "title": "擁抱真實的自己",
    "content": "接納是成長的開始。",
    "question": "如果接納自己，會發生什麼？",
    "breath": "gentle",
    "color": "#F0E8F4"
  },
  {
    "id": 334,
    "theme": "專注流域",
    "title": "臨在的力量",
    "content": "專注創造品質。",
    "question": "此刻我的感受是什麼？",
    "breath": "focus",
    "color": "#E8F0F8"
  },
  {
    "id": 335,
    "theme": "希望流域",
    "title": "困難終會過去",
    "content": "希望讓我們繼續前行。",
    "question": "我對未來抱持什麼樣的期待？",
    "breath": "hope",
    "color": "#FFF4E8"
  },
  {
    "id": 336,
    "theme": "平靜流域",
    "title": "放下控制",
    "content": "在當下找到安定。",
    "question": "我在抗拒什麼？",
    "breath": "calm",
    "color": "#E8F4F8"
  },
  {
    "id": 337,
    "theme": "行動流域",
    "title": "打破拖延的循環",
    "content": "前進比完美更重要。",
    "question": "完成這件事會帶給我什麼？",
    "breath": "energize",
    "color": "#FFE8D6"
  },
  {
    "id": 338,
    "theme": "共感流域",
    "title": "脆弱是勇氣",
    "content": "理解不需要相同。",
    "question": "我想被誰理解？我準備好了嗎？",
    "breath": "gentle",
    "color": "#D8E3E8"
  },
  {
    "id": 339,
    "theme": "修復流域",
    "title": "先陪自己安靜片刻",
    "content": "給自己時間復原。",
    "question": "此刻我需要如何被理解，才能感覺安心？",
    "breath": "restore",
    "color": "#E8F4E8"
  },
  {
    "id": 340,
    "theme": "接納流域",
    "title": "自我接納是力量",
    "content": "接納帶來自由。",
    "question": "我能接納自己的哪個部分？",
    "breath": "gentle",
    "color": "#F0E8F4"
  },
  {
    "id": 341,
    "theme": "專注流域",
    "title": "回到此刻的呼吸",
    "content": "此刻就是全部。",
    "question": "如何將注意力帶回此刻？",
    "breath": "focus",
    "color": "#E8F0F8"
  },
  {
    "id": 342,
    "theme": "希望流域",
    "title": "相信改變的力量",
    "content": "希望讓我們繼續前行。",
    "question": "我對未來抱持什麼樣的期待？",
    "breath": "hope",
    "color": "#FFF4E8"
  },
  {
    "id": 343,
    "theme": "平靜流域",
    "title": "內在的平靜",
    "content": "放下才能平靜。",
    "question": "我在抗拒什麼？",
    "breath": "calm",
    "color": "#E8F4F8"
  },
  {
    "id": 344,
    "theme": "行動流域",
    "title": "踏出第一步",
    "content": "行動帶來清晰。",
    "question": "完成這件事會帶給我什麼？",
    "breath": "energize",
    "color": "#FFE8D6"
  },
  {
    "id": 345,
    "theme": "共感流域",
    "title": "在關係中成長",
    "content": "表達需要也需要勇氣。",
    "question": "此刻我需要什麼樣的陪伴？",
    "breath": "gentle",
    "color": "#D8E3E8"
  },
  {
    "id": 346,
    "theme": "修復流域",
    "title": "給自己一點修復的時間",
    "content": "情緒需要被感受而非壓抑。",
    "question": "此刻我的身體想告訴我什麼？",
    "breath": "restore",
    "color": "#E8F4E8"
  },
  {
    "id": 347,
    "theme": "接納流域",
    "title": "擁抱真實的自己",
    "content": "你已經夠好了。",
    "question": "什麼讓我覺得自己不夠好？",
    "breath": "gentle",
    "color": "#F0E8F4"
  },
  {
    "id": 348,
    "theme": "專注流域",
    "title": "專注於眼前",
    "content": "專注帶來清明。",
    "question": "如何將注意力帶回此刻？",
    "breath": "focus",
    "color": "#E8F0F8"
  },
  {
    "id": 349,
    "theme": "希望流域",
    "title": "每天都是新開始",
    "content": "困境是暫時的。",
    "question": "我對未來抱持什麼樣的期待？",
    "breath": "hope",
    "color": "#FFF4E8"
  },
  {
    "id": 350,
    "theme": "平靜流域",
    "title": "在風暴中心",
    "content": "在當下找到安定。",
    "question": "我在抗拒什麼？",
    "breath": "calm",
    "color": "#E8F4F8"
  },
  {
    "id": 351,
    "theme": "行動流域",
    "title": "打破拖延的循環",
    "content": "一步步靠近理想。",
    "question": "什麼阻止了我開始？",
    "breath": "energize",
    "color": "#FFE8D6"
  },
  {
    "id": 352,
    "theme": "共感流域",
    "title": "同理心的力量",
    "content": "脆弱是連結的開始。",
    "question": "我想被誰理解？我準備好了嗎？",
    "breath": "gentle",
    "color": "#D8E3E8"
  },
  {
    "id": 353,
    "theme": "修復流域",
    "title": "溫柔對待自己",
    "content": "修復是持續的過程。",
    "question": "此刻我的身體想告訴我什麼？",
    "breath": "restore",
    "color": "#E8F4E8"
  },
  {
    "id": 354,
    "theme": "接納流域",
    "title": "善待內在小孩",
    "content": "接納是成長的開始。",
    "question": "什麼讓我覺得自己不夠好？",
    "breath": "gentle",
    "color": "#F0E8F4"
  },
  {
    "id": 355,
    "theme": "專注流域",
    "title": "一次只做一件事",
    "content": "當下是唯一真實存在的時刻。",
    "question": "如何將注意力帶回此刻？",
    "breath": "focus",
    "color": "#E8F0F8"
  },
  {
    "id": 356,
    "theme": "希望流域",
    "title": "希望是光",
    "content": "相信總會好轉。",
    "question": "我想創造什麼樣的未來？",
    "breath": "hope",
    "color": "#FFF4E8"
  },
  {
    "id": 357,
    "theme": "平靜流域",
    "title": "讓心安住在寧靜中",
    "content": "平靜是一種選擇。",
    "question": "此刻什麼能讓我感到平靜？",
    "breath": "calm",
    "color": "#E8F4F8"
  },
  {
    "id": 358,
    "theme": "行動流域",
    "title": "踏出第一步",
    "content": "開始永遠不會太遲。",
    "question": "此刻我可以採取哪個最小的行動？",
    "breath": "energize",
    "color": "#FFE8D6"
  },
  {
    "id": 359,
    "theme": "共感流域",
    "title": "被看見被接住",
    "content": "理解不需要相同。",
    "question": "我想被誰理解？我準備好了嗎？",
    "breath": "gentle",
    "color": "#D8E3E8"
  },
  {
    "id": 360,
    "theme": "修復流域",
    "title": "先陪自己安靜片刻",
    "content": "休息是為了走更長的路。",
    "question": "什麼能讓我感到被照顧？",
    "breath": "restore",
    "color": "#E8F4E8"
  },
  {
    "id": 361,
    "theme": "接納流域",
    "title": "善待內在小孩",
    "content": "不完美的自己，也值得被愛。",
    "question": "什麼讓我覺得自己不夠好？",
    "breath": "gentle",
    "color": "#F0E8F4"
  },
  {
    "id": 362,
    "theme": "專注流域",
    "title": "覺察此時此刻",
    "content": "覺察就是力量。",
    "question": "如何將注意力帶回此刻？",
    "breath": "focus",
    "color": "#E8F0F8"
  },
  {
    "id": 363,
    "theme": "希望流域",
    "title": "困難終會過去",
    "content": "困境是暫時的。",
    "question": "什麼讓我感到有希望？",
    "breath": "hope",
    "color": "#FFF4E8"
  },
  {
    "id": 364,
    "theme": "平靜流域",
    "title": "在風暴中心",
    "content": "在當下找到安定。",
    "question": "我在抗拒什麼？",
    "breath": "calm",
    "color": "#E8F4F8"
  },
  {
    "id": 365,
    "theme": "行動流域",
    "title": "現在就是最好的時機",
    "content": "每個行動都是改變的種子。",
    "question": "完成這件事會帶給我什麼？",
    "breath": "energize",
    "color": "#FFE8D6"
  },
  {
    "id": 366,
    "theme": "共感流域",
    "title": "在關係中成長",
    "content": "脆弱是連結的開始。",
    "question": "我能如何更真誠地表達？",
    "breath": "gentle",
    "color": "#D8E3E8"
  },
  {
    "id": 367,
    "theme": "修復流域",
    "title": "允許自己慢下來",
    "content": "情緒需要被感受而非壓抑。",
    "question": "此刻我需要如何被理解，才能感覺安心？",
    "breath": "restore",
    "color": "#E8F4E8"
  },
  {
    "id": 368,
    "theme": "接納流域",
    "title": "接納全部的自己",
    "content": "你已經夠好了。",
    "question": "什麼讓我覺得自己不夠好？",
    "breath": "gentle",
    "color": "#F0E8F4"
  },
  {
    "id": 369,
    "theme": "專注流域",
    "title": "當下是唯一真實",
    "content": "專注創造品質。",
    "question": "我在擔心什麼還未發生的事？",
    "breath": "focus",
    "color": "#E8F0F8"
  },
  {
    "id": 370,
    "theme": "希望流域",
    "title": "希望是光",
    "content": "未來充滿驚喜。",
    "question": "我想創造什麼樣的未來？",
    "breath": "hope",
    "color": "#FFF4E8"
  },
  {
    "id": 371,
    "theme": "平靜流域",
    "title": "接受不確定",
    "content": "平靜不是沒有風浪，而是學會與之共處。",
    "question": "我在抗拒什麼？",
    "breath": "calm",
    "color": "#E8F4F8"
  },
  {
    "id": 372,
    "theme": "行動流域",
    "title": "勇敢嘗試新事物",
    "content": "行動帶來清晰。",
    "question": "完成這件事會帶給我什麼？",
    "breath": "energize",
    "color": "#FFE8D6"
  },
  {
    "id": 373,
    "theme": "共感流域",
    "title": "允許自己被理解",
    "content": "理解不需要相同。",
    "question": "此刻我需要什麼樣的陪伴？",
    "breath": "gentle",
    "color": "#D8E3E8"
  },
  {
    "id": 374,
    "theme": "修復流域",
    "title": "身心需要休息",
    "content": "情緒需要被感受而非壓抑。",
    "question": "什麼能讓我感到被照顧？",
    "breath": "restore",
    "color": "#E8F4E8"
  },
  {
    "id": 375,
    "theme": "接納流域",
    "title": "接納全部的自己",
    "content": "接納帶來自由。",
    "question": "什麼讓我覺得自己不夠好？",
    "breath": "gentle",
    "color": "#F0E8F4"
  },
  {
    "id": 376,
    "theme": "專注流域",
    "title": "臨在的力量",
    "content": "覺察就是力量。",
    "question": "此刻我的感受是什麼？",
    "breath": "focus",
    "color": "#E8F0F8"
  },
  {
    "id": 377,
    "theme": "希望流域",
    "title": "困難終會過去",
    "content": "相信總會好轉。",
    "question": "我想創造什麼樣的未來？",
    "breath": "hope",
    "color": "#FFF4E8"
  },
  {
    "id": 378,
    "theme": "平靜流域",
    "title": "寧靜是答案",
    "content": "平靜是一種選擇。",
    "question": "此刻什麼能讓我感到平靜？",
    "breath": "calm",
    "color": "#E8F4F8"
  },
  {
    "id": 379,
    "theme": "行動流域",
    "title": "踏出第一步",
    "content": "一步步靠近理想。",
    "question": "什麼阻止了我開始？",
    "breath": "energize",
    "color": "#FFE8D6"
  },
  {
    "id": 380,
    "theme": "共感流域",
    "title": "理解彼此的差異",
    "content": "表達需要也需要勇氣。",
    "question": "我能如何更真誠地表達？",
    "breath": "gentle",
    "color": "#D8E3E8"
  },
  {
    "id": 381,
    "theme": "修復流域",
    "title": "允許自己慢下來",
    "content": "給自己時間復原。",
    "question": "什麼能讓我感到被照顧？",
    "breath": "restore",
    "color": "#E8F4E8"
  },
  {
    "id": 382,
    "theme": "接納流域",
    "title": "放下自我批判",
    "content": "完整包含光明與陰影。",
    "question": "如果接納自己，會發生什麼？",
    "breath": "gentle",
    "color": "#F0E8F4"
  },
  {
    "id": 383,
    "theme": "專注流域",
    "title": "覺察此時此刻",
    "content": "此刻就是全部。",
    "question": "我在擔心什麼還未發生的事？",
    "breath": "focus",
    "color": "#E8F0F8"
  },
  {
    "id": 384,
    "theme": "希望流域",
    "title": "保持期待",
    "content": "可能性永遠存在。",
    "question": "我對未來抱持什麼樣的期待？",
    "breath": "hope",
    "color": "#FFF4E8"
  },
  {
    "id": 385,
    "theme": "平靜流域",
    "title": "讓心安住在寧靜中",
    "content": "在當下找到安定。",
    "question": "我在抗拒什麼？",
    "breath": "calm",
    "color": "#E8F4F8"
  },
  {
    "id": 386,
    "theme": "行動流域",
    "title": "打破拖延的循環",
    "content": "一步步靠近理想。",
    "question": "此刻我可以採取哪個最小的行動？",
    "breath": "energize",
    "color": "#FFE8D6"
  },
  {
    "id": 387,
    "theme": "共感流域",
    "title": "理解彼此的差異",
    "content": "真實的自己值得被愛。",
    "question": "我能如何更真誠地表達？",
    "breath": "gentle",
    "color": "#D8E3E8"
  },
  {
    "id": 388,
    "theme": "修復流域",
    "title": "身心需要休息",
    "content": "再向外分享溫柔與在意。",
    "question": "此刻我需要如何被理解，才能感覺安心？",
    "breath": "restore",
    "color": "#E8F4E8"
  },
  {
    "id": 389,
    "theme": "接納流域",
    "title": "善待內在小孩",
    "content": "你已經夠好了。",
    "question": "什麼讓我覺得自己不夠好？",
    "breath": "gentle",
    "color": "#F0E8F4"
  },
  {
    "id": 390,
    "theme": "專注流域",
    "title": "專注於眼前",
    "content": "活在當下減少焦慮。",
    "question": "此刻我的感受是什麼？",
    "breath": "focus",
    "color": "#E8F0F8"
  },
  {
    "id": 391,
    "theme": "希望流域",
    "title": "困難終會過去",
    "content": "可能性永遠存在。",
    "question": "我對未來抱持什麼樣的期待？",
    "breath": "hope",
    "color": "#FFF4E8"
  },
  {
    "id": 392,
    "theme": "平靜流域",
    "title": "讓心安住在寧靜中",
    "content": "平靜是一種選擇。",
    "question": "我在抗拒什麼？",
    "breath": "calm",
    "color": "#E8F4F8"
  },
  {
    "id": 393,
    "theme": "行動流域",
    "title": "踏出第一步",
    "content": "每個行動都是改變的種子。",
    "question": "完成這件事會帶給我什麼？",
    "breath": "energize",
    "color": "#FFE8D6"
  },
  {
    "id": 394,
    "theme": "共感流域",
    "title": "在關係中成長",
    "content": "同在就是支持。",
    "question": "我能如何更真誠地表達？",
    "breath": "gentle",
    "color": "#D8E3E8"
  },
  {
    "id": 395,
    "theme": "修復流域",
    "title": "身心需要休息",
    "content": "情緒需要被感受而非壓抑。",
    "question": "什麼能讓我感到被照顧？",
    "breath": "restore",
    "color": "#E8F4E8"
  },
  {
    "id": 396,
    "theme": "接納流域",
    "title": "擁抱真實的自己",
    "content": "接納帶來自由。",
    "question": "我能接納自己的哪個部分？",
    "breath": "gentle",
    "color": "#F0E8F4"
  },
  {
    "id": 397,
    "theme": "專注流域",
    "title": "專注於眼前",
    "content": "覺察就是力量。",
    "question": "此刻我的感受是什麼？",
    "breath": "focus",
    "color": "#E8F0F8"
  },
  {
    "id": 398,
    "theme": "希望流域",
    "title": "黎明前的黑暗",
    "content": "相信總會好轉。",
    "question": "我想創造什麼樣的未來？",
    "breath": "hope",
    "color": "#FFF4E8"
  },
  {
    "id": 399,
    "theme": "平靜流域",
    "title": "接受不確定",
    "content": "平靜是一種選擇。",
    "question": "如何在不確定中找到安定？",
    "breath": "calm",
    "color": "#E8F4F8"
  },
  {
    "id": 400,
    "theme": "行動流域",
    "title": "行動創造可能",
    "content": "前進比完美更重要。",
    "question": "完成這件事會帶給我什麼？",
    "breath": "energize",
    "color": "#FFE8D6"
  },
  {
    "id": 401,
    "theme": "共感流域",
    "title": "同理心的力量",
    "content": "表達需要也需要勇氣。",
    "question": "此刻我需要什麼樣的陪伴？",
    "breath": "gentle",
    "color": "#D8E3E8"
  },
  {
    "id": 402,
    "theme": "修復流域",
    "title": "先陪自己安靜片刻",
    "content": "修復是持續的過程。",
    "question": "此刻我的身體想告訴我什麼？",
    "breath": "restore",
    "color": "#E8F4E8"
  },
  {
    "id": 403,
    "theme": "接納流域",
    "title": "擁抱真實的自己",
    "content": "每個部分都有存在的意義。",
    "question": "什麼讓我覺得自己不夠好？",
    "breath": "gentle",
    "color": "#F0E8F4"
  },
  {
    "id": 404,
    "theme": "專注流域",
    "title": "一次只做一件事",
    "content": "覺察就是力量。",
    "question": "我在擔心什麼還未發生的事？",
    "breath": "focus",
    "color": "#E8F0F8"
  },
  {
    "id": 405,
    "theme": "希望流域",
    "title": "未來仍有無限可能",
    "content": "可能性永遠存在。",
    "question": "我想創造什麼樣的未來？",
    "breath": "hope",
    "color": "#FFF4E8"
  },
  {
    "id": 406,
    "theme": "平靜流域",
    "title": "讓心安住在寧靜中",
    "content": "平靜是一種選擇。",
    "question": "如何在不確定中找到安定？",
    "breath": "calm",
    "color": "#E8F4F8"
  },
  {
    "id": 407,
    "theme": "行動流域",
    "title": "小步前進也是進步",
    "content": "開始永遠不會太遲。",
    "question": "什麼阻止了我開始？",
    "breath": "energize",
    "color": "#FFE8D6"
  },
  {
    "id": 408,
    "theme": "共感流域",
    "title": "被看見被接住",
    "content": "聆聽比建議更重要。",
    "question": "我能如何更真誠地表達？",
    "breath": "gentle",
    "color": "#D8E3E8"
  },
  {
    "id": 409,
    "theme": "修復流域",
    "title": "療癒需要耐心",
    "content": "休息是為了走更長的路。",
    "question": "什麼能讓我感到被照顧？",
    "breath": "restore",
    "color": "#E8F4E8"
  },
  {
    "id": 410,
    "theme": "接納流域",
    "title": "自我接納是力量",
    "content": "每個部分都有存在的意義。",
    "question": "什麼讓我覺得自己不夠好？",
    "breath": "gentle",
    "color": "#F0E8F4"
  },
  {
    "id": 411,
    "theme": "專注流域",
    "title": "一次只做一件事",
    "content": "專注帶來清明。",
    "question": "此刻我的感受是什麼？",
    "breath": "focus",
    "color": "#E8F0F8"
  },
  {
    "id": 412,
    "theme": "希望流域",
    "title": "相信美好會到來",
    "content": "困境是暫時的。",
    "question": "什麼讓我感到有希望？",
    "breath": "hope",
    "color": "#FFF4E8"
  },
  {
    "id": 413,
    "theme": "平靜流域",
    "title": "讓心安住在寧靜中",
    "content": "在當下找到安定。",
    "question": "我在抗拒什麼？",
    "breath": "calm",
    "color": "#E8F4F8"
  },
  {
    "id": 414,
    "theme": "行動流域",
    "title": "現在就是最好的時機",
    "content": "從小事開始改變。",
    "question": "此刻我可以採取哪個最小的行動？",
    "breath": "energize",
    "color": "#FFE8D6"
  },
  {
    "id": 415,
    "theme": "共感流域",
    "title": "在關係中成長",
    "content": "真實的自己值得被愛。",
    "question": "我能如何更真誠地表達？",
    "breath": "gentle",
    "color": "#D8E3E8"
  },
  {
    "id": 416,
    "theme": "修復流域",
    "title": "身心需要休息",
    "content": "情緒需要被感受而非壓抑。",
    "question": "此刻我需要如何被理解，才能感覺安心？",
    "breath": "restore",
    "color": "#E8F4E8"
  },
  {
    "id": 417,
    "theme": "接納流域",
    "title": "這樣的我也很好",
    "content": "每個部分都有存在的意義。",
    "question": "如果接納自己，會發生什麼？",
    "breath": "gentle",
    "color": "#F0E8F4"
  },
  {
    "id": 418,
    "theme": "專注流域",
    "title": "臨在的力量",
    "content": "專注創造品質。",
    "question": "如何將注意力帶回此刻？",
    "breath": "focus",
    "color": "#E8F0F8"
  },
  {
    "id": 419,
    "theme": "希望流域",
    "title": "黎明前的黑暗",
    "content": "每個今天都是新的開始。",
    "question": "我對未來抱持什麼樣的期待？",
    "breath": "hope",
    "color": "#FFF4E8"
  },
  {
    "id": 420,
    "theme": "平靜流域",
    "title": "放下控制",
    "content": "寧靜來自內在。",
    "question": "此刻什麼能讓我感到平靜？",
    "breath": "calm",
    "color": "#E8F4F8"
  },
  {
    "id": 421,
    "theme": "行動流域",
    "title": "打破拖延的循環",
    "content": "開始永遠不會太遲。",
    "question": "完成這件事會帶給我什麼？",
    "breath": "energize",
    "color": "#FFE8D6"
  },
  {
    "id": 422,
    "theme": "共感流域",
    "title": "允許自己被理解",
    "content": "聆聽比建議更重要。",
    "question": "此刻我需要什麼樣的陪伴？",
    "breath": "gentle",
    "color": "#D8E3E8"
  },
  {
    "id": 423,
    "theme": "修復流域",
    "title": "先陪自己安靜片刻",
    "content": "再向外分享溫柔與在意。",
    "question": "此刻我需要如何被理解，才能感覺安心？",
    "breath": "restore",
    "color": "#E8F4E8"
  },
  {
    "id": 424,
    "theme": "接納流域",
    "title": "不完美也值得被愛",
    "content": "接納是成長的開始。",
    "question": "我能接納自己的哪個部分？",
    "breath": "gentle",
    "color": "#F0E8F4"
  },
  {
    "id": 425,
    "theme": "專注流域",
    "title": "臨在的力量",
    "content": "當下是唯一真實存在的時刻。",
    "question": "如何將注意力帶回此刻？",
    "breath": "focus",
    "color": "#E8F0F8"
  },
  {
    "id": 426,
    "theme": "希望流域",
    "title": "未來仍有無限可能",
    "content": "未來充滿驚喜。",
    "question": "什麼讓我感到有希望？",
    "breath": "hope",
    "color": "#FFF4E8"
  },
  {
    "id": 427,
    "theme": "平靜流域",
    "title": "在混亂中保持平靜",
    "content": "放下才能平靜。",
    "question": "如何在不確定中找到安定？",
    "breath": "calm",
    "color": "#E8F4F8"
  },
  {
    "id": 428,
    "theme": "行動流域",
    "title": "相信行動的力量",
    "content": "一步步靠近理想。",
    "question": "此刻我可以採取哪個最小的行動？",
    "breath": "energize",
    "color": "#FFE8D6"
  },
  {
    "id": 429,
    "theme": "共感流域",
    "title": "連結從聆聽開始",
    "content": "聆聽比建議更重要。",
    "question": "我想被誰理解？我準備好了嗎？",
    "breath": "gentle",
    "color": "#D8E3E8"
  },
  {
    "id": 430,
    "theme": "修復流域",
    "title": "先陪自己安靜片刻",
    "content": "療癒不需要完美，只需要開始。",
    "question": "此刻我需要如何被理解，才能感覺安心？",
    "breath": "restore",
    "color": "#E8F4E8"
  },
  {
    "id": 431,
    "theme": "接納流域",
    "title": "放下自我批判",
    "content": "每個部分都有存在的意義。",
    "question": "什麼讓我覺得自己不夠好？",
    "breath": "gentle",
    "color": "#F0E8F4"
  },
  {
    "id": 432,
    "theme": "專注流域",
    "title": "專注於眼前",
    "content": "專注帶來清明。",
    "question": "如何將注意力帶回此刻？",
    "breath": "focus",
    "color": "#E8F0F8"
  },
  {
    "id": 433,
    "theme": "希望流域",
    "title": "黎明前的黑暗",
    "content": "希望讓我們繼續前行。",
    "question": "我對未來抱持什麼樣的期待？",
    "breath": "hope",
    "color": "#FFF4E8"
  },
  {
    "id": 434,
    "theme": "平靜流域",
    "title": "在風暴中心",
    "content": "在當下找到安定。",
    "question": "此刻什麼能讓我感到平靜？",
    "breath": "calm",
    "color": "#E8F4F8"
  },
  {
    "id": 435,
    "theme": "行動流域",
    "title": "踏出第一步",
    "content": "從小事開始改變。",
    "question": "此刻我可以採取哪個最小的行動？",
    "breath": "energize",
    "color": "#FFE8D6"
  },
  {
    "id": 436,
    "theme": "共感流域",
    "title": "連結從聆聽開始",
    "content": "脆弱是連結的開始。",
    "question": "此刻我需要什麼樣的陪伴？",
    "breath": "gentle",
    "color": "#D8E3E8"
  },
  {
    "id": 437,
    "theme": "修復流域",
    "title": "身心需要休息",
    "content": "休息是為了走更長的路。",
    "question": "此刻我的身體想告訴我什麼？",
    "breath": "restore",
    "color": "#E8F4E8"
  },
  {
    "id": 438,
    "theme": "接納流域",
    "title": "放下自我批判",
    "content": "接納帶來自由。",
    "question": "什麼讓我覺得自己不夠好？",
    "breath": "gentle",
    "color": "#F0E8F4"
  },
  {
    "id": 439,
    "theme": "專注流域",
    "title": "覺察此時此刻",
    "content": "活在當下減少焦慮。",
    "question": "此刻我的感受是什麼？",
    "breath": "focus",
    "color": "#E8F0F8"
  },
  {
    "id": 440,
    "theme": "希望流域",
    "title": "保持期待",
    "content": "可能性永遠存在。",
    "question": "我想創造什麼樣的未來？",
    "breath": "hope",
    "color": "#FFF4E8"
  },
  {
    "id": 441,
    "theme": "平靜流域",
    "title": "在混亂中保持平靜",
    "content": "寧靜來自內在。",
    "question": "我在抗拒什麼？",
    "breath": "calm",
    "color": "#E8F4F8"
  },
  {
    "id": 442,
    "theme": "行動流域",
    "title": "踏出第一步",
    "content": "開始永遠不會太遲。",
    "question": "完成這件事會帶給我什麼？",
    "breath": "energize",
    "color": "#FFE8D6"
  },
  {
    "id": 443,
    "theme": "共感流域",
    "title": "脆弱是勇氣",
    "content": "同在就是支持。",
    "question": "此刻我需要什麼樣的陪伴？",
    "breath": "gentle",
    "color": "#D8E3E8"
  },
  {
    "id": 444,
    "theme": "修復流域",
    "title": "修復是一種智慧",
    "content": "療癒不需要完美，只需要開始。",
    "question": "什麼能讓我感到被照顧？",
    "breath": "restore",
    "color": "#E8F4E8"
  },
  {
    "id": 445,
    "theme": "接納流域",
    "title": "放下自我批判",
    "content": "你已經夠好了。",
    "question": "如果接納自己，會發生什麼？",
    "breath": "gentle",
    "color": "#F0E8F4"
  },
  {
    "id": 446,
    "theme": "專注流域",
    "title": "專注於眼前",
    "content": "當下是唯一真實存在的時刻。",
    "question": "我在擔心什麼還未發生的事？",
    "breath": "focus",
    "color": "#E8F0F8"
  },
  {
    "id": 447,
    "theme": "希望流域",
    "title": "相信改變的力量",
    "content": "可能性永遠存在。",
    "question": "什麼讓我感到有希望？",
    "breath": "hope",
    "color": "#FFF4E8"
  },
  {
    "id": 448,
    "theme": "平靜流域",
    "title": "讓心安住在寧靜中",
    "content": "平靜是一種選擇。",
    "question": "如何在不確定中找到安定？",
    "breath": "calm",
    "color": "#E8F4F8"
  },
  {
    "id": 449,
    "theme": "行動流域",
    "title": "相信行動的力量",
    "content": "每個行動都是改變的種子。",
    "question": "此刻我可以採取哪個最小的行動？",
    "breath": "energize",
    "color": "#FFE8D6"
  },
  {
    "id": 450,
    "theme": "共感流域",
    "title": "脆弱是勇氣",
    "content": "同在就是支持。",
    "question": "我能如何更真誠地表達？",
    "breath": "gentle",
    "color": "#D8E3E8"
  },
  {
    "id": 451,
    "theme": "修復流域",
    "title": "先陪自己安靜片刻",
    "content": "休息是為了走更長的路。",
    "question": "什麼能讓我感到被照顧？",
    "breath": "restore",
    "color": "#E8F4E8"
  },
  {
    "id": 452,
    "theme": "接納流域",
    "title": "這樣的我也很好",
    "content": "每個部分都有存在的意義。",
    "question": "我能接納自己的哪個部分？",
    "breath": "gentle",
    "color": "#F0E8F4"
  },
  {
    "id": 453,
    "theme": "專注流域",
    "title": "專注於眼前",
    "content": "活在當下減少焦慮。",
    "question": "我在擔心什麼還未發生的事？",
    "breath": "focus",
    "color": "#E8F0F8"
  },
  {
    "id": 454,
    "theme": "希望流域",
    "title": "未來仍有無限可能",
    "content": "未來充滿驚喜。",
    "question": "我對未來抱持什麼樣的期待？",
    "breath": "hope",
    "color": "#FFF4E8"
  },
  {
    "id": 455,
    "theme": "平靜流域",
    "title": "接受不確定",
    "content": "平靜不是沒有風浪，而是學會與之共處。",
    "question": "此刻什麼能讓我感到平靜？",
    "breath": "calm",
    "color": "#E8F4F8"
  },
  {
    "id": 456,
    "theme": "行動流域",
    "title": "踏出第一步",
    "content": "每個行動都是改變的種子。",
    "question": "完成這件事會帶給我什麼？",
    "breath": "energize",
    "color": "#FFE8D6"
  },
  {
    "id": 457,
    "theme": "共感流域",
    "title": "理解彼此的差異",
    "content": "同在就是支持。",
    "question": "我能如何更真誠地表達？",
    "breath": "gentle",
    "color": "#D8E3E8"
  },
  {
    "id": 458,
    "theme": "修復流域",
    "title": "接受情緒的起伏",
    "content": "情緒需要被感受而非壓抑。",
    "question": "此刻我的身體想告訴我什麼？",
    "breath": "restore",
    "color": "#E8F4E8"
  },
  {
    "id": 459,
    "theme": "接納流域",
    "title": "這樣的我也很好",
    "content": "不完美的自己，也值得被愛。",
    "question": "如果接納自己，會發生什麼？",
    "breath": "gentle",
    "color": "#F0E8F4"
  },
  {
    "id": 460,
    "theme": "專注流域",
    "title": "活在當下",
    "content": "活在當下減少焦慮。",
    "question": "此刻我的感受是什麼？",
    "breath": "focus",
    "color": "#E8F0F8"
  },
  {
    "id": 461,
    "theme": "希望流域",
    "title": "每天都是新開始",
    "content": "相信總會好轉。",
    "question": "我對未來抱持什麼樣的期待？",
    "breath": "hope",
    "color": "#FFF4E8"
  },
  {
    "id": 462,
    "theme": "平靜流域",
    "title": "接受不確定",
    "content": "平靜不是沒有風浪，而是學會與之共處。",
    "question": "我在抗拒什麼？",
    "breath": "calm",
    "color": "#E8F4F8"
  },
  {
    "id": 463,
    "theme": "行動流域",
    "title": "小步前進也是進步",
    "content": "開始永遠不會太遲。",
    "question": "完成這件事會帶給我什麼？",
    "breath": "energize",
    "color": "#FFE8D6"
  },
  {
    "id": 464,
    "theme": "共感流域",
    "title": "脆弱是勇氣",
    "content": "同在就是支持。",
    "question": "我想被誰理解？我準備好了嗎？",
    "breath": "gentle",
    "color": "#D8E3E8"
  },
  {
    "id": 465,
    "theme": "修復流域",
    "title": "先陪自己安靜片刻",
    "content": "再向外分享溫柔與在意。",
    "question": "此刻我的身體想告訴我什麼？",
    "breath": "restore",
    "color": "#E8F4E8"
  },
  {
    "id": 466,
    "theme": "接納流域",
    "title": "不完美也值得被愛",
    "content": "每個部分都有存在的意義。",
    "question": "什麼讓我覺得自己不夠好？",
    "breath": "gentle",
    "color": "#F0E8F4"
  },
  {
    "id": 467,
    "theme": "專注流域",
    "title": "放下過去與未來",
    "content": "此刻就是全部。",
    "question": "如何將注意力帶回此刻？",
    "breath": "focus",
    "color": "#E8F0F8"
  },
  {
    "id": 468,
    "theme": "希望流域",
    "title": "相信美好會到來",
    "content": "可能性永遠存在。",
    "question": "什麼讓我感到有希望？",
    "breath": "hope",
    "color": "#FFF4E8"
  },
  {
    "id": 469,
    "theme": "平靜流域",
    "title": "在風暴中心",
    "content": "平靜是一種選擇。",
    "question": "我在抗拒什麼？",
    "breath": "calm",
    "color": "#E8F4F8"
  },
  {
    "id": 470,
    "theme": "行動流域",
    "title": "相信行動的力量",
    "content": "一步步靠近理想。",
    "question": "什麼阻止了我開始？",
    "breath": "energize",
    "color": "#FFE8D6"
  },
  {
    "id": 471,
    "theme": "共感流域",
    "title": "同理心的力量",
    "content": "表達需要也需要勇氣。",
    "question": "我能如何更真誠地表達？",
    "breath": "gentle",
    "color": "#D8E3E8"
  },
  {
    "id": 472,
    "theme": "修復流域",
    "title": "先陪自己安靜片刻",
    "content": "給自己時間復原。",
    "question": "此刻我的身體想告訴我什麼？",
    "breath": "restore",
    "color": "#E8F4E8"
  },
  {
    "id": 473,
    "theme": "接納流域",
    "title": "擁抱真實的自己",
    "content": "你已經夠好了。",
    "question": "什麼讓我覺得自己不夠好？",
    "breath": "gentle",
    "color": "#F0E8F4"
  },
  {
    "id": 474,
    "theme": "專注流域",
    "title": "當下是唯一真實",
    "content": "當下是唯一真實存在的時刻。",
    "question": "如何將注意力帶回此刻？",
    "breath": "focus",
    "color": "#E8F0F8"
  },
  {
    "id": 475,
    "theme": "希望流域",
    "title": "困難終會過去",
    "content": "未來充滿驚喜。",
    "question": "我想創造什麼樣的未來？",
    "breath": "hope",
    "color": "#FFF4E8"
  },
  {
    "id": 476,
    "theme": "平靜流域",
    "title": "寧靜是答案",
    "content": "寧靜來自內在。",
    "question": "我在抗拒什麼？",
    "breath": "calm",
    "color": "#E8F4F8"
  },
  {
    "id": 477,
    "theme": "行動流域",
    "title": "現在就是最好的時機",
    "content": "一步步靠近理想。",
    "question": "什麼阻止了我開始？",
    "breath": "energize",
    "color": "#FFE8D6"
  },
  {
    "id": 478,
    "theme": "共感流域",
    "title": "被看見被接住",
    "content": "聆聽比建議更重要。",
    "question": "此刻我需要什麼樣的陪伴？",
    "breath": "gentle",
    "color": "#D8E3E8"
  },
  {
    "id": 479,
    "theme": "修復流域",
    "title": "給自己一點修復的時間",
    "content": "休息是為了走更長的路。",
    "question": "此刻我的身體想告訴我什麼？",
    "breath": "restore",
    "color": "#E8F4E8"
  },
  {
    "id": 480,
    "theme": "接納流域",
    "title": "這樣的我也很好",
    "content": "你已經夠好了。",
    "question": "如果接納自己，會發生什麼？",
    "breath": "gentle",
    "color": "#F0E8F4"
  },
  {
    "id": 481,
    "theme": "專注流域",
    "title": "一次只做一件事",
    "content": "專注帶來清明。",
    "question": "我在擔心什麼還未發生的事？",
    "breath": "focus",
    "color": "#E8F0F8"
  },
  {
    "id": 482,
    "theme": "希望流域",
    "title": "黎明前的黑暗",
    "content": "每個今天都是新的開始。",
    "question": "什麼讓我感到有希望？",
    "breath": "hope",
    "color": "#FFF4E8"
  },
  {
    "id": 483,
    "theme": "平靜流域",
    "title": "寧靜是答案",
    "content": "寧靜來自內在。",
    "question": "此刻什麼能讓我感到平靜？",
    "breath": "calm",
    "color": "#E8F4F8"
  },
  {
    "id": 484,
    "theme": "行動流域",
    "title": "小步前進也是進步",
    "content": "從小事開始改變。",
    "question": "此刻我可以採取哪個最小的行動？",
    "breath": "energize",
    "color": "#FFE8D6"
  },
  {
    "id": 485,
    "theme": "共感流域",
    "title": "理解彼此的差異",
    "content": "理解不需要相同。",
    "question": "此刻我需要什麼樣的陪伴？",
    "breath": "gentle",
    "color": "#D8E3E8"
  },
  {
    "id": 486,
    "theme": "修復流域",
    "title": "身心需要休息",
    "content": "給自己時間復原。",
    "question": "此刻我的身體想告訴我什麼？",
    "breath": "restore",
    "color": "#E8F4E8"
  },
  {
    "id": 487,
    "theme": "接納流域",
    "title": "這樣的我也很好",
    "content": "不完美的自己，也值得被愛。",
    "question": "什麼讓我覺得自己不夠好？",
    "breath": "gentle",
    "color": "#F0E8F4"
  },
  {
    "id": 488,
    "theme": "專注流域",
    "title": "放下過去與未來",
    "content": "專注創造品質。",
    "question": "此刻我的感受是什麼？",
    "breath": "focus",
    "color": "#E8F0F8"
  },
  {
    "id": 489,
    "theme": "希望流域",
    "title": "相信美好會到來",
    "content": "困境是暫時的。",
    "question": "我想創造什麼樣的未來？",
    "breath": "hope",
    "color": "#FFF4E8"
  },
  {
    "id": 490,
    "theme": "平靜流域",
    "title": "讓心安住在寧靜中",
    "content": "平靜是一種選擇。",
    "question": "我在抗拒什麼？",
    "breath": "calm",
    "color": "#E8F4F8"
  },
  {
    "id": 491,
    "theme": "行動流域",
    "title": "踏出第一步",
    "content": "開始永遠不會太遲。",
    "question": "此刻我可以採取哪個最小的行動？",
    "breath": "energize",
    "color": "#FFE8D6"
  },
  {
    "id": 492,
    "theme": "共感流域",
    "title": "同理心的力量",
    "content": "真實的自己值得被愛。",
    "question": "我能如何更真誠地表達？",
    "breath": "gentle",
    "color": "#D8E3E8"
  },
  {
    "id": 493,
    "theme": "修復流域",
    "title": "療癒需要耐心",
    "content": "情緒需要被感受而非壓抑。",
    "question": "此刻我需要如何被理解，才能感覺安心？",
    "breath": "restore",
    "color": "#E8F4E8"
  },
  {
    "id": 494,
    "theme": "接納流域",
    "title": "不完美也值得被愛",
    "content": "完整包含光明與陰影。",
    "question": "如果接納自己，會發生什麼？",
    "breath": "gentle",
    "color": "#F0E8F4"
  },
  {
    "id": 495,
    "theme": "專注流域",
    "title": "回到此刻的呼吸",
    "content": "專注創造品質。",
    "question": "如何將注意力帶回此刻？",
    "breath": "focus",
    "color": "#E8F0F8"
  },
  {
    "id": 496,
    "theme": "希望流域",
    "title": "每天都是新開始",
    "content": "困境是暫時的。",
    "question": "我對未來抱持什麼樣的期待？",
    "breath": "hope",
    "color": "#FFF4E8"
  },
  {
    "id": 497,
    "theme": "平靜流域",
    "title": "寧靜是答案",
    "content": "平靜不是沒有風浪，而是學會與之共處。",
    "question": "此刻什麼能讓我感到平靜？",
    "breath": "calm",
    "color": "#E8F4F8"
  },
  {
    "id": 498,
    "theme": "行動流域",
    "title": "相信行動的力量",
    "content": "行動帶來清晰。",
    "question": "完成這件事會帶給我什麼？",
    "breath": "energize",
    "color": "#FFE8D6"
  },
  {
    "id": 499,
    "theme": "共感流域",
    "title": "被看見被接住",
    "content": "理解不需要相同。",
    "question": "我想被誰理解？我準備好了嗎？",
    "breath": "gentle",
    "color": "#D8E3E8"
  },
  {
    "id": 500,
    "theme": "修復流域",
    "title": "接受情緒的起伏",
    "content": "休息是為了走更長的路。",
    "question": "什麼能讓我感到被照顧？",
    "breath": "restore",
    "color": "#E8F4E8"
  }
]